Workbook
Name SegmentaciónDeDatos_Ex_date_Efectos1: #N/A
Name SegmentaciónDeDatos_Ex_date_Efectos11: #N/A
Name SegmentaciónDeDatos_Tipo_Valor__Mexico: #N/A

Sheet Posición
A1: Posición | B1: Portfolio | C1: Tipo Valor (Mexico) | D1: Ex date/Efectos | E1: Fecha Registro | F1: Fecha Pago | G1: Tipo de derecho | H1: Estatus | I1: Proporción/importe | J1: Pos Dividendo | K1: ISIN | L1: =TODAY() -> 46230
A2: =IF(H2="APLICADO","SI","NO") -> NO | B2: =Covaf!B2 -> AXAIM29 | C2: =CONCATENATE(Covaf!E2,"_",Covaf!F2,"_",Covaf!G2) -> I_BANOBRA_26295 | D2: =IFERROR(VLOOKUP(C2,BIVA!$C$3:$J$5311,3,0),"") | E2: =IFERROR(VLOOKUP(C2,BIVA!$C$3:$J$5311,4,0),"") | F2: =IFERROR(VLOOKUP(C2,BIVA!$C$3:$J$5311,5,0),"") | G2: =IFERROR(VLOOKUP(C2,BIVA!$C$3:$J$5311,6,0),"") | H2: =IFERROR(VLOOKUP(C2,BIVA!$C$3:$J$5311,7,0),"") | I2: =IFERROR(VLOOKUP(C2,BIVA!$C$3:$J$5311,8,0),"") | J2: =Covaf!H2 -> 199956 | K2: =Covaf!X2 -> MX0IBA064X15
A3: =IF(H3="APLICADO","SI","NO") -> NO | B3: =Covaf!B3 -> AXAIM29 | C3: =CONCATENATE(Covaf!E3,"_",Covaf!F3,"_",Covaf!G3) -> M_BONOS_270603 | D3: =IFERROR(VLOOKUP(C3,BIVA!$C$3:$J$5311,3,0),"") | E3: =IFERROR(VLOOKUP(C3,BIVA!$C$3:$J$5311,4,0),"") | F3: =IFERROR(VLOOKUP(C3,BIVA!$C$3:$J$5311,5,0),"") | G3: =IFERROR(VLOOKUP(C3,BIVA!$C$3:$J$5311,6,0),"") | H3: =IFERROR(VLOOKUP(C3,BIVA!$C$3:$J$5311,7,0),"") | I3: =IFERROR(VLOOKUP(C3,BIVA!$C$3:$J$5311,8,0),"") | J3: =Covaf!H3 -> 8800 | K3: =Covaf!X3 -> MX0MGO0000D8
A4: =IF(H4="APLICADO","SI","NO") -> NO | B4: =Covaf!B4 -> AXAIM29 | C4: =CONCATENATE(Covaf!E4,"_",Covaf!F4,"_",Covaf!G4) -> S_UDIBONO_261203 | D4: =IFERROR(VLOOKUP(C4,BIVA!$C$3:$J$5311,3,0),"") | E4: =IFERROR(VLOOKUP(C4,BIVA!$C$3:$J$5311,4,0),"") | F4: =IFERROR(VLOOKUP(C4,BIVA!$C$3:$J$5311,5,0),"") | G4: =IFERROR(VLOOKUP(C4,BIVA!$C$3:$J$5311,6,0),"") | H4: =IFERROR(VLOOKUP(C4,BIVA!$C$3:$J$5311,7,0),"") | I4: =IFERROR(VLOOKUP(C4,BIVA!$C$3:$J$5311,8,0),"") | J4: =Covaf!H4 -> 127 | K4: =Covaf!X4 -> MX0SGO0000M6
A5: =IF(H5="APLICADO","SI","NO") -> NO | B5: =Covaf!B5 -> AXAIM29 | C5: =CONCATENATE(Covaf!E5,"_",Covaf!F5,"_",Covaf!G5) -> 1I_VT_* | D5: =IFERROR(VLOOKUP(C5,BIVA!$C$3:$J$5311,3,0),"") | E5: =IFERROR(VLOOKUP(C5,BIVA!$C$3:$J$5311,4,0),"") | F5: =IFERROR(VLOOKUP(C5,BIVA!$C$3:$J$5311,5,0),"") | G5: =IFERROR(VLOOKUP(C5,BIVA!$C$3:$J$5311,6,0),"") | H5: =IFERROR(VLOOKUP(C5,BIVA!$C$3:$J$5311,7,0),"") | I5: =IFERROR(VLOOKUP(C5,BIVA!$C$3:$J$5311,8,0),"") | J5: =Covaf!H5 -> 146 | K5: =Covaf!X5 -> US9220427424
A6: =IF(H6="APLICADO","SI","NO") -> NO | B6: =Covaf!B6 -> AXAIM41 | C6: =CONCATENATE(Covaf!E6,"_",Covaf!F6,"_",Covaf!G6) -> I_BANOBRA_26295 | D6: =IFERROR(VLOOKUP(C6,BIVA!$C$3:$J$5311,3,0),"") | E6: =IFERROR(VLOOKUP(C6,BIVA!$C$3:$J$5311,4,0),"") | F6: =IFERROR(VLOOKUP(C6,BIVA!$C$3:$J$5311,5,0),"") | G6: =IFERROR(VLOOKUP(C6,BIVA!$C$3:$J$5311,6,0),"") | H6: =IFERROR(VLOOKUP(C6,BIVA!$C$3:$J$5311,7,0),"") | I6: =IFERROR(VLOOKUP(C6,BIVA!$C$3:$J$5311,8,0),"") | J6: =Covaf!H6 -> 251674 | K6: =Covaf!X6 -> MX0IBA064X15
A7: =IF(H7="APLICADO","SI","NO") -> NO | B7: =Covaf!B7 -> AXAIM41 | C7: =CONCATENATE(Covaf!E7,"_",Covaf!F7,"_",Covaf!G7) -> M_BONOS_290531 | D7: =IFERROR(VLOOKUP(C7,BIVA!$C$3:$J$5311,3,0),"") | E7: =IFERROR(VLOOKUP(C7,BIVA!$C$3:$J$5311,4,0),"") | F7: =IFERROR(VLOOKUP(C7,BIVA!$C$3:$J$5311,5,0),"") | G7: =IFERROR(VLOOKUP(C7,BIVA!$C$3:$J$5311,6,0),"") | H7: =IFERROR(VLOOKUP(C7,BIVA!$C$3:$J$5311,7,0),"") | I7: =IFERROR(VLOOKUP(C7,BIVA!$C$3:$J$5311,8,0),"") | J7: =Covaf!H7 -> 7300 | K7: =Covaf!X7 -> MX0MGO0000H9
A8: =IF(H8="APLICADO","SI","NO") -> NO | B8: =Covaf!B8 -> AXAIM41 | C8: =CONCATENATE(Covaf!E8,"_",Covaf!F8,"_",Covaf!G8) -> S_UDIBONO_261203 | D8: =IFERROR(VLOOKUP(C8,BIVA!$C$3:$J$5311,3,0),"") | E8: =IFERROR(VLOOKUP(C8,BIVA!$C$3:$J$5311,4,0),"") | F8: =IFERROR(VLOOKUP(C8,BIVA!$C$3:$J$5311,5,0),"") | G8: =IFERROR(VLOOKUP(C8,BIVA!$C$3:$J$5311,6,0),"") | H8: =IFERROR(VLOOKUP(C8,BIVA!$C$3:$J$5311,7,0),"") | I8: =IFERROR(VLOOKUP(C8,BIVA!$C$3:$J$5311,8,0),"") | J8: =Covaf!H8 -> 174 | K8: =Covaf!X8 -> MX0SGO0000M6
A9: =IF(H9="APLICADO","SI","NO") -> NO | B9: =Covaf!B9 -> AXAIM41 | C9: =CONCATENATE(Covaf!E9,"_",Covaf!F9,"_",Covaf!G9) -> 1I_VT_* | D9: =IFERROR(VLOOKUP(C9,BIVA!$C$3:$J$5311,3,0),"") | E9: =IFERROR(VLOOKUP(C9,BIVA!$C$3:$J$5311,4,0),"") | F9: =IFERROR(VLOOKUP(C9,BIVA!$C$3:$J$5311,5,0),"") | G9: =IFERROR(VLOOKUP(C9,BIVA!$C$3:$J$5311,6,0),"") | H9: =IFERROR(VLOOKUP(C9,BIVA!$C$3:$J$5311,7,0),"") | I9: =IFERROR(VLOOKUP(C9,BIVA!$C$3:$J$5311,8,0),"") | J9: =Covaf!H9 -> 203 | K9: =Covaf!X9 -> US9220427424
A10: =IF(H10="APLICADO","SI","NO") -> NO | B10: =Covaf!B10 -> AXAIM53 | C10: =CONCATENATE(Covaf!E10,"_",Covaf!F10,"_",Covaf!G10) -> I_BANOBRA_26295 | D10: =IFERROR(VLOOKUP(C10,BIVA!$C$3:$J$5311,3,0),"") | E10: =IFERROR(VLOOKUP(C10,BIVA!$C$3:$J$5311,4,0),"") | F10: =IFERROR(VLOOKUP(C10,BIVA!$C$3:$J$5311,5,0),"") | G10: =IFERROR(VLOOKUP(C10,BIVA!$C$3:$J$5311,6,0),"") | H10: =IFERROR(VLOOKUP(C10,BIVA!$C$3:$J$5311,7,0),"") | I10: =IFERROR(VLOOKUP(C10,BIVA!$C$3:$J$5311,8,0),"") | J10: =Covaf!H10 -> 234586 | K10: =Covaf!X10 -> MX0IBA064X15
A11: =IF(H11="APLICADO","SI","NO") -> NO | B11: =Covaf!B11 -> AXAIM53 | C11: =CONCATENATE(Covaf!E11,"_",Covaf!F11,"_",Covaf!G11) -> M_BONOS_290531 | D11: =IFERROR(VLOOKUP(C11,BIVA!$C$3:$J$5311,3,0),"") | E11: =IFERROR(VLOOKUP(C11,BIVA!$C$3:$J$5311,4,0),"") | F11: =IFERROR(VLOOKUP(C11,BIVA!$C$3:$J$5311,5,0),"") | G11: =IFERROR(VLOOKUP(C11,BIVA!$C$3:$J$5311,6,0),"") | H11: =IFERROR(VLOOKUP(C11,BIVA!$C$3:$J$5311,7,0),"") | I11: =IFERROR(VLOOKUP(C11,BIVA!$C$3:$J$5311,8,0),"") | J11: =Covaf!H11 -> 5600 | K11: =Covaf!X11 -> MX0MGO0000H9
A12: =IF(H12="APLICADO","SI","NO") -> NO | B12: =Covaf!B12 -> AXAIM53 | C12: =CONCATENATE(Covaf!E12,"_",Covaf!F12,"_",Covaf!G12) -> S_UDIBONO_261203 | D12: =IFERROR(VLOOKUP(C12,BIVA!$C$3:$J$5311,3,0),"") | E12: =IFERROR(VLOOKUP(C12,BIVA!$C$3:$J$5311,4,0),"") | F12: =IFERROR(VLOOKUP(C12,BIVA!$C$3:$J$5311,5,0),"") | G12: =IFERROR(VLOOKUP(C12,BIVA!$C$3:$J$5311,6,0),"") | H12: =IFERROR(VLOOKUP(C12,BIVA!$C$3:$J$5311,7,0),"") | I12: =IFERROR(VLOOKUP(C12,BIVA!$C$3:$J$5311,8,0),"") | J12: =Covaf!H12 -> 183 | K12: =Covaf!X12 -> MX0SGO0000M6
A13: =IF(H13="APLICADO","SI","NO") -> NO | B13: =Covaf!B13 -> AXAIM53 | C13: =CONCATENATE(Covaf!E13,"_",Covaf!F13,"_",Covaf!G13) -> 1I_VT_* | D13: =IFERROR(VLOOKUP(C13,BIVA!$C$3:$J$5311,3,0),"") | E13: =IFERROR(VLOOKUP(C13,BIVA!$C$3:$J$5311,4,0),"") | F13: =IFERROR(VLOOKUP(C13,BIVA!$C$3:$J$5311,5,0),"") | G13: =IFERROR(VLOOKUP(C13,BIVA!$C$3:$J$5311,6,0),"") | H13: =IFERROR(VLOOKUP(C13,BIVA!$C$3:$J$5311,7,0),"") | I13: =IFERROR(VLOOKUP(C13,BIVA!$C$3:$J$5311,8,0),"") | J13: =Covaf!H13 -> 244 | K13: =Covaf!X13 -> US9220427424
... A5576: =IF(H5576="APLICADO","SI","NO") -> NO | B5576: =Covaf!B5576 -> 0 | C5576: =CONCATENATE(Covaf!E5576,"_",Covaf!F5576,"_",Covaf!G5576) -> __ | D5576: =IFERROR(VLOOKUP(C5576,BIVA!$C$3:$J$5311,3,0),"") | E5576: =IFERROR(VLOOKUP(C5576,BIVA!$C$3:$J$5311,4,0),"") | F5576: =IFERROR(VLOOKUP(C5576,BIVA!$C$3:$J$5311,5,0),"") | G5576: =IFERROR(VLOOKUP(C5576,BIVA!$C$3:$J$5311,6,0),"") | H5576: =IFERROR(VLOOKUP(C5576,BIVA!$C$3:$J$5311,7,0),"") | I5576: =IFERROR(VLOOKUP(C5576,BIVA!$C$3:$J$5311,8,0),"") | J5576: =Covaf!H5576 -> 0 | K5576: =Covaf!X5576 -> 0

Sheet BIVA
A1: Clave | B1: Serie | C1: Emisión | D1: ISIN | E1: Ex date/Efectos | F1: Registro | G1: Pago | H1: Tipo de derecho | I1: Estatus | J1: Proporción/importe | K1: Moneda | L1: Importe
A2: CATMRCK | B2: 17 | C2: 1R_CATMRCK_17 | D2: MX1RCA260007 | E2: 24/07/2026 | F2: 24/07/2026 | G2: 27/07/2026 | H2: Distribución en efectivo | I2: Aplicado | J2: 0.25157955097 MXN | K2: MXN | L2: $0.25157955097 | M2: 378,286,039
A3: FVIA | B3: 16 | C3: FF_FVIA_16,17 | D3: MXFFFV000007 | E3: 24/07/2026 | F3: 24/07/2026 | G3: 27/07/2026 | H3: Distribución en efectivo | I3: Aplicado | J3: SERIE(S) '16' CUPON VIGENTE 0 CUPON PAGO 0 A MXN $ 0.3889785940707460 | K3: MXN | L3: $0.388978594070746
A4: LIVCK | B4: 15 | C4: 1R_LIVCK_15 | D4: MX1RLI0A0002 | E4: 24/07/2026 | F4: 24/07/2026 | G4: 27/07/2026 | H4: Reembolso | I4: Aplicado | J4: 0.014759274420067 MXN | K4: MXN | L4: $0.014759274420067 | M4: 8,450,279,902
A5: NXXMFCK | B5: 18 | C5: 1R_NXXMFCK_18 | D5: MX1RNX000007 | E5: 24/07/2026 | F5: 24/07/2026 | G5: 27/07/2026 | H5: Reembolso | I5: Aplicado | J5: 6.83848666802134 MXN | K5: MXN | L5: $6.83848666802134 | M5: 7,165,328
A6: FFLA4CK | B6: 15 | C6: 1R_FFLA4CK_15 | D6: MX1RFF040005 | E6: 27/07/2026 | F6: 27/07/2026 | G6: 28/07/2026 | H6: Reembolso | I6: Aplicado | J6: 6.3733224950393 MXN | K6: MXN | L6: $6.3733224950393 | M6: 1,114,259
A7: LOCK3PI | B7: 21 | C7: 1R_LOCK3PI_21 | D7: MX1RLO060004 | E7: 27/07/2026 | F7: 27/07/2026 | G7: 28/07/2026 | H7: Reembolso | I7: Aplicado | J7: 0.328504508778 USD | K7: USD | L7: $0.328504508778 | M7: 657,717
A8: LOCK3PI | B8: 21-2 | C8: 1R_LOCK3PI_21-2 | D8: MX1RLO060012 | E8: 27/07/2026 | F8: 27/07/2026 | G8: 28/07/2026 | H8: Reembolso | I8: Aplicado | J8: 0.3035633701322 USD | K8: USD | L8: $0.3035633701322 | M8: 3,089,042
A9: PLA2CK | B9: 17 | C9: 1R_PLA2CK_17 | D9: MX1RPL0Q0009 | E9: 27/07/2026 | F9: 27/07/2026 | G9: 28/07/2026 | H9: Distribución en efectivo | I9: Aplicado | J9: SERIE(S) '17' CUPON VIGENTE 0 CUPON PAGO 0 A MXN $ 0.098587880568 | K9: MXN | L9: $0.098587880568
A10: FANVIPI | B10: 23 | C10: 1R_FANVIPI_23 | D10: MX1RFA0E0007 | E10: 24/07/2026 | F10: 24/07/2026 | G10: 29/07/2026 | H10: Suscripción | I10: Aplicado | J10: 1 Actuales X 0.1051768540502 Nuevos a 100 USD | K10: USD | N10: $100 | O10: 104,550
A11: CAPI | B11: 22-2 | C11: 1R_CAPI_22-2 | D11: MX1RCA210010 | E11: 27/07/2026 | F11: 27/07/2026 | G11: 30/07/2026 | H11: Suscripción | I11: Aplicado | J11: 1 Actuales X 0.0015452605971 Nuevos a 100 USD | K11: USD | N11: $100 | O11: 1,621
A12: CAPI | B12: 22-3 | C12: 1R_CAPI_22-3 | D12: MX1RCA210028 | E12: 27/07/2026 | F12: 27/07/2026 | G12: 30/07/2026 | H12: Suscripción | I12: Aplicado | J12: 1 Actuales X 0.001380232281 Nuevos a 100 USD | K12: USD | N12: $100 | O12: 1,621
A13: CAPI | B13: 23-4 | C13: 1R_CAPI_23-4 | D13: MX1RCA210069 | E13: 27/07/2026 | F13: 27/07/2026 | G13: 30/07/2026 | H13: Suscripción | I13: Aplicado | J13: 1 Actuales X 0.006137568561 Nuevos a 100 USD | K13: USD | N13: $100 | O13: 5,360
A14: CAPI | B14: 23-5 | C14: 1R_CAPI_23-5 | D14: MX1RCA210077 | E14: 27/07/2026 | F14: 27/07/2026 | G14: 30/07/2026 | H14: Suscripción | I14: Aplicado | J14: 1 Actuales X 0.0061713999693 Nuevos a 100 USD | K14: USD | N14: $100 | O14: 5,425
A15: CAPI | B15: 23-6 | C15: 1R_CAPI_23-6 | D15: MX1RCA210085 | E15: 27/07/2026 | F15: 27/07/2026 | G15: 30/07/2026 | H15: Suscripción | I15: Aplicado | J15: 1 Actuales X 0.0062123821652 Nuevos a 100 USD | K15: USD | N15: $100 | O15: 5,425
A16: GLOB1PI | B16: 22-17 | C16: 1R_GLOB1PI_22-17 | D16: MX1RGL0300G8 | E16: 27/07/2026 | F16: 27/07/2026 | G16: 30/07/2026 | H16: Suscripción | I16: Aplicado | J16: 1 Actuales X 0.0147286821706 Nuevos a 100 USD | K16: USD | N16: $100 | O16: 4,503
A17: GLOB1PI | B17: 22-18 | C17: 1R_GLOB1PI_22-18 | D17: MX1RGL0300H6 | E17: 27/07/2026 | F17: 27/07/2026 | G17: 30/07/2026 | H17: Suscripción | I17: Aplicado | J17: 1 Actuales X 0.0125531314946 Nuevos a 100 USD | K17: USD | N17: $100 | O17: 6,010
A18: GLOB1PI | B18: 22-19 | C18: 1R_GLOB1PI_22-19 | D18: MX1RGL0300I4 | E18: 27/07/2026 | F18: 27/07/2026 | G18: 30/07/2026 | H18: Suscripción | I18: Aplicado | J18: 1 Actuales X 0.012449947483 Nuevos a 100 USD | K18: USD | N18: $100 | O18: 6,946
A19: GLOB1PI | B19: 22-20 | C19: 1R_GLOB1PI_22-20 | D19: MX1RGL0300J2 | E19: 27/07/2026 | F19: 27/07/2026 | G19: 30/07/2026 | H19: Suscripción | I19: Aplicado | J19: 1 Actuales X 0.0122696128842 Nuevos a 100 USD | K19: USD | N19: $100 | O19: 6,932
A20: GLOB1PI | B20: 22-21 | C20: 1R_GLOB1PI_22-21 | D20: MX1RGL0300K0 | E20: 27/07/2026 | F20: 27/07/2026 | G20: 30/07/2026 | H20: Suscripción | I20: Aplicado | J20: 1 Actuales X 0.0121254795168 Nuevos a 100 USD | K20: USD | N20: $100 | O20: 7,801
A21: GLOB1PI | B21: 22-22 | C21: 1R_GLOB1PI_22-22 | D21: MX1RGL0300L8 | E21: 27/07/2026 | F21: 27/07/2026 | G21: 30/07/2026 | H21: Suscripción | I21: Aplicado | J21: 1 Actuales X 0.0117956493118 Nuevos a 100 USD | K21: USD | N21: $100 | O21: 7,920
... A24: KANANPI | B24: 24-G | C24: 1R_KANANPI_24-G | D24: MX1RKA000080 | E24: 27/07/2026 | F24: 27/07/2026 | G24: 30/07/2026 | H24: Suscripción | I24: Aplicado | J24: 1 Actuales X 0.970783860553 Nuevos a 100 USD | K24: USD | N24: $100 | O24: 220,100
A25: COST | B25: * | C25: 1A_COST_* | D25: US22160K1051 | E25: 24/07/2026 | F25: 24/07/2026 | G25: 07/08/2026 | H25: Dividendo en efectivo | I25: Aplicado | J25: Option Number: "001" Option Type: "Cash" Default Option: "Yes" Gross Dividend Rate: "1.47 USD" Option Number: "002" Option Type: "Security" Default Option: "No"
A26: DX2X | B26: N | C26: 1I_DX2X_N | D26: LU0328475792 | E26: 24/07/2026 | H26: Otro | I26: Informativo
A27: GEHC | B27: * | C27: 1A_GEHC_* | D27: US36266G1076 | E27: 24/07/2026 | F27: 24/07/2026 | G27: 14/08/2026 | H27: Dividendo en efectivo | I27: Aplicado | J27: Option Number: "001" Option Type: "Cash" Default Option: "Yes" Gross Dividend Rate: "0.035 USD" Option Number: "002" Option Type: "Security" Default Option: "No"
A28: KPN | B28: N | C28: 1A_KPN_N | D28: NL0000009082 | E28: 24/07/2026 | F28: 27/07/2026 | G28: 03/08/2026 | H28: Dividendo en efectivo | I28: Aplicado | J28: Option Number: "001" Option Type: "Cash" Default Option: "Yes" Gross Dividend Rate: "0.08 EUR" Net Dividend Rate: "0.068 EUR"
A29: PFE | B29: * | C29: 1A_PFE_* | D29: US7170811035 | E29: 24/07/2026 | F29: 24/07/2026 | G29: 01/09/2026 | H29: Dividendo en efectivo | I29: Aplicado | J29: Option Number: "001" Option Type: "Cash" Default Option: "Yes" Gross Dividend Rate: "0.43 USD" Option Number: "002" Option Type: "Security" Default Option: "No"
A30: PG | B30: * | C30: 1A_PG_* | D30: US7427181091 | E30: 24/07/2026 | F30: 24/07/2026 | G30: 17/08/2026 | H30: Dividendo en efectivo | I30: Aplicado | J30: Option Number: "001" Option Type: "Cash" Default Option: "Yes" Gross Dividend Rate: "1.0885 USD" Option Number: "002" Option Type: "Security" Default Option: "No"
A31: PNR | B31: N | C31: 1A_PNR_N | D31: IE00BLS09M33 | E31: 24/07/2026 | F31: 24/07/2026 | G31: 07/08/2026 | H31: Dividendo en efectivo | I31: Aplicado | J31: Option Number: "001" Option Type: "Cash" Default Option: "Yes" Gross Dividend Rate: "0.27 USD"
A32: TMHC | B32: * | C32: 1A_TMHC_* | D32: US87724P1066 | E32: 24/07/2026 | H32: Fusión | I32: Aplicado | J32: Option Number: "001" Option Type: "Cash" Default Option: "Yes" Generic Cash Price Received Per Product: "72.5 USD" - "1.0" Unit
A33: ASML | B33: N | C33: 1A_ASML_N | D33: NL0010273215 | E33: 27/07/2026 | F33: 28/07/2026 | G33: 05/08/2026 | H33: Dividendo en efectivo | I33: Aplicado | J33: Option Number: "001" Option Type: "Cash" Default Option: "Yes" Gross Dividend Rate: "1.88 EUR" Net Dividend Rate: "1.598 EUR"
A34: BNY | B34: * | C34: 1A_BNY_* | D34: US0640581007 | E34: 27/07/2026 | F34: 27/07/2026 | G34: 07/08/2026 | H34: Dividendo en efectivo | I34: Aplicado | J34: Option Number: "001" Option Type: "Cash" Default Option: "Yes" Gross Dividend Rate: "0.63 USD" Option Number: "002" Option Type: "Security" Default Option: "No"
A35: NOKIA | B35: N | C35: 1A_NOKIA_N | D35: FI0009000681 | E35: 27/07/2026 | F35: 28/07/2026 | G35: 06/08/2026 | H35: Dividendo en efectivo | I35: Aplicado | J35: Option Number: "001" Option Type: "Cash" Default Option: "Yes" Gross Dividend Rate: "0.04 EUR" Net Dividend Rate: "0.026 EUR"
A36: QBTS | B36: * | C36: 1A_QBTS_* | D36: US26740W1099 | E36: 27/07/2026 | H36: Canje simple | I36: Aplicado
A37: RY | B37: N | C37: 1A_RY_N | D37: CA7800871021 | E37: 27/07/2026 | F37: 27/07/2026 | G37: 24/08/2026 | H37: Dividendo en efectivo | I37: Aplicado | J37: Option Number: "001" Option Type: "Cash" Default Option: "Yes" Gross Dividend Rate: "1.76 CAD" Net Dividend Rate: "1.32 CAD"
A38: WIT | B38: N | C38: 1A_WIT_N | D38: US97651M1099 | E38: 27/07/2026 | F38: 27/07/2026 | H38: Dividendo en efectivo | I38: Aplicado | J38: Option Number: "001" Option Type: "Cash" Default Option: "Yes" Gross Dividend Rate: "0.020775 USD" Net Dividend Rate: "0.018507 USD" Option Number: "002" Option Type: "Security" Default Option: "No"

Sheet Covaf
B1: CVE_FONDO | C1: FECHA | D1: CVE_TEN | E1: CVE_BMV | F1: EMISORA | G1: SERIE | H1: TIT_FDIA | I1: CTO_FDIA | J1: PRECIO | K1: IMP_MDO | L1: DIAS_UH | M1: DIAS_EQ | N1: TASA_POND | O1: TASA_EQ | P1: FINICIO | Q1: FVENCE | R1: DIAS_CPN | S1: ACT_TOT | T1: ACT_NET | U1: EMISOR | V1: CLS_FONDO | W1: ACT_BASE | X1: ISIN | Y1: BURSATIL_CALIFIC
B2: AXAIM29 | C2: 23/07/2026 | D2: D | E2: I | F2: BANOBRA | G2: 26295 | H2: 199956 | I2: 1 | J2: 1 | K2: 199956 | L2: 0 | M2: 0 | N2: 0 | O2: 0 | P2: 25/06/2026 | Q2: 24/07/2026 | R2: 0 | S2: 1601532.5 | T2: 1600949.7 | U2: BANOBRA | V2: RVDIS | W2: 1601532.5 | X2: MX0IBA064X15 | Y2: mxA-1+
B3: AXAIM29 | C3: 23/07/2026 | D3: D | E3: M | F3: BONOS | G3: 270603 | H3: 8800 | I3: 101.03 | J3: 101.63723 | K3: 894407.6 | L3: 314 | M3: 0 | N3: 7.5 | O3: 0 | P3: 28/12/2006 | Q3: 03/06/2027 | R3: 132 | S3: 1601532.5 | T3: 1600949.7 | U3: GOBMEX | V3: RVDIS | W3: 1601532.5 | X3: MX0MGO0000D8 | Y3: HR AAA
B4: AXAIM29 | C4: 23/07/2026 | D4: D | E4: S | F4: UDIBONO | G4: 261203 | H4: 127 | I4: 866.24 | J4: 884.25062 | K4: 112299.83 | L4: 132 | M4: 0 | N4: 3 | O4: 0 | P4: 09/12/2021 | Q4: 03/12/2026 | R4: 132 | S4: 1601532.5 | T4: 1600949.7 | U4: GOBMEX | V4: RVDIS | W4: 1601532.5 | X4: MX0SGO0000M6 | Y4: HR AAA
B5: AXAIM29 | C5: 23/07/2026 | D5: D | E5: 1I | F5: VT | G5: * | H5: 146 | I5: 2540.21 | J5: 2704.5759 | K5: 394868.09 | L5: 0 | M5: 0 | N5: 0 | O5: 0 | P5: 20/10/2009 | R5: 0 | S5: 1601532.5 | T5: 1600949.7 | U5: VT | V5: RVDIS | W5: 1601532.5 | X5: US9220427424 | Y5: N/A
B6: AXAIM41 | C6: 23/07/2026 | D6: D | E6: I | F6: BANOBRA | G6: 26295 | H6: 251674 | I6: 1 | J6: 1 | K6: 251674 | L6: 0 | M6: 0 | N6: 0 | O6: 0 | P6: 25/06/2026 | Q6: 24/07/2026 | R6: 0 | S6: 1700879.4 | T6: 1700353.9 | U6: BANOBRA | V6: RVDIS | W6: 1700829.4 | X6: MX0IBA064X15 | Y6: mxA-1+
B7: AXAIM41 | C7: 23/07/2026 | D7: D | E7: M | F7: BONOS | G7: 290531 | H7: 7300 | I7: 102.16 | J7: 102.22827 | K7: 746266.34 | L7: 1042 | M7: 0 | N7: 8.5 | O7: 0 | P7: 24/12/2008 | Q7: 31/05/2029 | R7: 132 | S7: 1700879.4 | T7: 1700353.9 | U7: GOBMEX | V7: RVDIS | W7: 1700829.4 | X7: MX0MGO0000H9 | Y7: HR AAA
B8: AXAIM41 | C8: 23/07/2026 | D8: D | E8: S | F8: UDIBONO | G8: 261203 | H8: 174 | I8: 866.24 | J8: 884.25062 | K8: 153859.61 | L8: 132 | M8: 0 | N8: 3 | O8: 0 | P8: 09/12/2021 | Q8: 03/12/2026 | R8: 132 | S8: 1700879.4 | T8: 1700353.9 | U8: GOBMEX | V8: RVDIS | W8: 1700829.4 | X8: MX0SGO0000M6 | Y8: HR AAA
B9: AXAIM41 | C9: 23/07/2026 | D9: D | E9: 1I | F9: VT | G9: * | H9: 203 | I9: 2540.21 | J9: 2704.5759 | K9: 549028.92 | L9: 0 | M9: 0 | N9: 0 | O9: 0 | P9: 20/10/2009 | R9: 0 | S9: 1700879.4 | T9: 1700353.9 | U9: VT | V9: RVDIS | W9: 1700829.4 | X9: US9220427424 | Y9: N/A
B10: AXAIM53 | C10: 23/07/2026 | D10: D | E10: I | F10: BANOBRA | G10: 26295 | H10: 234586 | I10: 1 | J10: 1 | K10: 234586 | L10: 0 | M10: 0 | N10: 0 | O10: 0 | P10: 25/06/2026 | Q10: 24/07/2026 | R10: 0 | S10: 1628798.8 | T10: 1628365.2 | U10: BANOBRA | V10: RVDIS | W10: 1628798.8 | X10: MX0IBA064X15 | Y10: mxA-1+
B11: AXAIM53 | C11: 23/07/2026 | D11: D | E11: M | F11: BONOS | G11: 290531 | H11: 5600 | I11: 102.16 | J11: 102.22827 | K11: 572478.29 | L11: 1042 | M11: 0 | N11: 8.5 | O11: 0 | P11: 24/12/2008 | Q11: 31/05/2029 | R11: 132 | S11: 1628798.8 | T11: 1628365.2 | U11: GOBMEX | V11: RVDIS | W11: 1628798.8 | X11: MX0MGO0000H9 | Y11: HR AAA
B12: AXAIM53 | C12: 23/07/2026 | D12: D | E12: S | F12: UDIBONO | G12: 261203 | H12: 183 | I12: 866.24 | J12: 884.25062 | K12: 161817.86 | L12: 132 | M12: 0 | N12: 3 | O12: 0 | P12: 09/12/2021 | Q12: 03/12/2026 | R12: 132 | S12: 1628798.8 | T12: 1628365.2 | U12: GOBMEX | V12: RVDIS | W12: 1628798.8 | X12: MX0SGO0000M6 | Y12: HR AAA
B13: AXAIM53 | C13: 23/07/2026 | D13: D | E13: 1I | F13: VT | G13: * | H13: 244 | I13: 2540.21 | J13: 2704.5759 | K13: 659916.53 | L13: 0 | M13: 0 | N13: 0 | O13: 0 | P13: 20/10/2009 | R13: 0 | S13: 1628798.8 | T13: 1628365.2 | U13: VT | V13: RVDIS | W13: 1628798.8 | X13: US9220427424 | Y13: N/A
B14: AXAIM65 | C14: 23/07/2026 | D14: D | E14: I | F14: BANOBRA | G14: 26295 | H14: 124733 | I14: 1 | J14: 1 | K14: 124733 | L14: 0 | M14: 0 | N14: 0 | O14: 0 | P14: 25/06/2026 | Q14: 24/07/2026 | R14: 0 | S14: 1855876.6 | T14: 1855716.8 | U14: BANOBRA | V14: RVDIS | W14: 1855876.6 | X14: MX0IBA064X15 | Y14: mxA-1+
B15: AXAIM65 | C15: 23/07/2026 | D15: D | E15: M | F15: BONOS | G15: 290531 | H15: 700 | I15: 102.16 | J15: 102.22827 | K15: 71559.79 | L15: 1042 | M15: 0 | N15: 8.5 | O15: 0 | P15: 24/12/2008 | Q15: 31/05/2029 | R15: 132 | S15: 1855876.6 | T15: 1855716.8 | U15: GOBMEX | V15: RVDIS | W15: 1855876.6 | X15: MX0MGO0000H9 | Y15: HR AAA
B16: AXAIM65 | C16: 23/07/2026 | D16: D | E16: S | F16: UDIBONO | G16: 261203 | H16: 216 | I16: 866.24 | J16: 884.25062 | K16: 190998.13 | L16: 132 | M16: 0 | N16: 3 | O16: 0 | P16: 09/12/2021 | Q16: 03/12/2026 | R16: 132 | S16: 1855876.6 | T16: 1855716.8 | U16: GOBMEX | V16: RVDIS | W16: 1855876.6 | X16: MX0SGO0000M6 | Y16: HR AAA
B17: AXAIM65 | C17: 23/07/2026 | D17: D | E17: 1I | F17: VT | G17: * | H17: 543 | I17: 2540.21 | J17: 2704.5759 | K17: 1468584.7 | L17: 0 | M17: 0 | N17: 0 | O17: 0 | P17: 20/10/2009 | R17: 0 | S17: 1855876.6 | T17: 1855716.8 | U17: VT | V17: RVDIS | W17: 1855876.6 | X17: US9220427424 | Y17: N/A
B18: DEUDAOP | C18: 23/07/2026 | D18: D | E18: BI | F18: CETES | G18: 280412 | H18: 136358900 | I18: 8.62 | J18: 8.782073 | K18: 1197513814 | L18: 628 | M18: 0 | N18: 6.982 | O18: 0 | P18: 23/04/2026 | Q18: 12/04/2028 | R18: 0 | S18: 2.9562998e+10 | T18: 2.9136856e+10 | U18: GOBMEX | V18: IDDIS | W18: 2.9176666e+10 | X18: MXBIGO000YY4 | Y18: HR+1
B19: DEUDAOP | C19: 23/07/2026 | D19: D | E19: BI | F19: CETES | G19: 280217 | H19: 89099875 | I19: 8.65 | J19: 8.907592 | K19: 7.9366533e+08 | L19: 573 | M19: 0 | N19: 6.863 | O19: 0 | P19: 26/02/2026 | Q19: 17/02/2028 | R19: 0 | S19: 2.9562998e+10 | T19: 2.9136856e+10 | U19: GOBMEX | V19: IDDIS | W19: 2.9176666e+10 | X19: MXBIGO000YP2 | Y19: HR+1
B20: DEUDAOP | C20: 23/07/2026 | D20: D | E20: BI | F20: CETES | G20: 270902 | H20: 197000000 | I20: 8.83 | J20: 9.247807 | K20: 1821817979 | L20: 405 | M20: 0 | N20: 6.686 | O20: 0 | P20: 11/09/2025 | Q20: 02/09/2027 | R20: 0 | S20: 2.9562998e+10 | T20: 2.9136856e+10 | U20: GOBMEX | V20: IDDIS | W20: 2.9176666e+10 | X20: MXBIGO000Y59 | Y20: HR+1
B21: DEUDAOP | C21: 23/07/2026 | D21: D | E21: BI | F21: CETES | G21: 260820 | H21: 14535000 | I21: 9.55 | J21: 9.951784 | K21: 1.4464918e+08 | L21: 27 | M21: 0 | N21: 6.429 | O21: 0 | P21: 21/08/2025 | Q21: 20/08/2026 | R21: 0 | S21: 2.9562998e+10 | T21: 2.9136856e+10 | U21: GOBMEX | V21: IDDIS | W21: 2.9176666e+10 | X21: MXBIGO000Y34 | Y21: HR+1
B22: DEUDAOP | C22: 23/07/2026 | D22: D | E22: BI | F22: CETES | G22: 260917 | H22: 85682400 | I22: 9.73 | J22: 9.901147 | K22: 8.4835404e+08 | L22: 55 | M22: 0 | N22: 6.47 | O22: 0 | P22: 18/09/2025 | Q22: 17/09/2026 | R22: 0 | S22: 2.9562998e+10 | T22: 2.9136856e+10 | U22: GOBMEX | V22: IDDIS | W22: 2.9176666e+10 | X22: MXBIGO000WN1 | Y22: HR+1
B23: DEUDAOP | C23: 23/07/2026 | D23: D | E23: BI | F23: CETES | G23: 261001 | H23: 26330000 | I23: 9.47 | J23: 9.875828 | K23: 2.6003055e+08 | L23: 69 | M23: 0 | N23: 6.479 | O23: 0 | P23: 10/10/2024 | Q23: 01/10/2026 | R23: 0 | S23: 2.9562998e+10 | T23: 2.9136856e+10 | U23: GOBMEX | V23: IDDIS | W23: 2.9176666e+10 | X23: MXBIGO000WO9 | Y23: HR+1
B24: DEUDAOP | C24: 23/07/2026 | D24: D | E24: BI | F24: CETES | G24: 270708 | H24: 273148662 | I24: 8.93 | J24: 9.361114 | K24: 2.5569758e+09 | L24: 349 | M24: 0 | N24: 6.59 | O24: 0 | P24: 17/07/2025 | Q24: 08/07/2027 | R24: 0 | S24: 2.9562998e+10 | T24: 2.9136856e+10 | U24: GOBMEX | V24: IDDIS | W24: 2.9176666e+10 | X24: MXBIGO000XW0 | Y24: HR+1
B25: DEUDAOP | C25: 23/07/2026 | D25: D | E25: BI | F25: CETES | G25: 261210 | H25: 40054109 | I25: 9.33 | J25: 9.748196 | K25: 3.9045531e+08 | L25: 139 | M25: 0 | N25: 6.522 | O25: 0 | P25: 11/12/2025 | Q25: 10/12/2026 | R25: 0 | S25: 2.9562998e+10 | T25: 2.9136856e+10 | U25: GOBMEX | V25: IDDIS | W25: 2.9176666e+10 | X25: MXBIGO000YI7 | Y25: HR+1
B26: DEUDAOP | C26: 23/07/2026 | D26: D | E26: BI | F26: CETES | G26: 270121 | H26: 86175200 | I26: 9.25 | J26: 9.670824 | K26: 8.3338519e+08 | L26: 181 | M26: 0 | N26: 6.547 | O26: 0 | P26: 30/01/2025 | Q26: 21/01/2027 | R26: 0 | S26: 2.9562998e+10 | T26: 2.9136856e+10 | U26: GOBMEX | V26: IDDIS | W26: 2.9176666e+10 | X26: MXBIGO000X68 | Y26: HR+1
B27: DEUDAOP | C27: 23/07/2026 | D27: D | E27: BI | F27: CETES | G27: 270318 | H27: 59050000 | I27: 9.14 | J27: 9.570309 | K27: 5.6512675e+08 | L27: 237 | M27: 0 | N27: 6.527 | O27: 0 | P27: 27/03/2025 | Q27: 18/03/2027 | R27: 0 | S27: 2.9562998e+10 | T27: 2.9136856e+10 | U27: GOBMEX | V27: IDDIS | W27: 2.9176666e+10 | X27: MXBIGO000XE8 | Y27: HR+1
B28: DEUDAOP | C28: 23/07/2026 | D28: D | E28: BI | F28: CETES | G28: 270429 | H28: 16199060 | I28: 9.32 | J28: 9.496237 | K28: 1.5383011e+08 | L28: 279 | M28: 0 | N28: 6.5 | O28: 0 | P28: 30/04/2026 | Q28: 29/04/2027 | R28: 0 | S28: 2.9562998e+10 | T28: 2.9136856e+10 | U28: GOBMEX | V28: IDDIS | W28: 2.9176666e+10 | X28: MXBIGO000Z09 | Y28: HR+1
B29: DEUDAOP | C29: 23/07/2026 | D29: D | E29: BI | F29: CETES | G29: 270513 | H29: 93000000 | I29: 9.03 | J29: 9.464631 | K29: 880210683 | L29: 293 | M29: 0 | N29: 6.578 | O29: 0 | P29: 22/05/2025 | Q29: 13/05/2027 | R29: 0 | S29: 2.9562998e+10 | T29: 2.9136856e+10 | U29: GOBMEX | V29: IDDIS | W29: 2.9176666e+10 | X29: MXBIGO000XO7 | Y29: HR+1
B30: DEUDAOP | C30: 23/07/2026 | D30: D | E30: BI | F30: CETES | G30: 261126 | H30: 45000000 | I30: 9.36 | J30: 9.772982 | K30: 439784190 | L30: 125 | M30: 0 | N30: 6.538 | O30: 0 | P30: 05/12/2024 | Q30: 26/11/2026 | R30: 0 | S30: 2.9562998e+10 | T30: 2.9136856e+10 | U30: GOBMEX | V30: IDDIS | W30: 2.9176666e+10 | X30: MXBIGO000WW2 | Y30: HR+1
B31: DEUDAOP | C31: 23/07/2026 | D31: D | E31: CHD | F31: BSANT | G31: 2945000 | H31: 44298 | I31: 17.99 | J31: 17.5269 | K31: 776415.91 | L31: 0 | M31: 0 | N31: 0 | O31: 0 | P31: 02/02/2021 | R31: 0 | S31: 2.9562998e+10 | T31: 2.9136856e+10 | U31: BANSAN | V31: IDDIS | W31: 2.9176666e+10 | Y31: N/A
B32: DEUDAOP | C32: 23/07/2026 | D32: D | E32: CHD | F32: JPMOR | G32: 3584000 | H32: 104921 | I32: 18.04 | J32: 17.565558 | K32: 1843009.9 | L32: 0 | M32: 0 | N32: 3.5 | O32: 0 | P32: 02/02/2021 | R32: 0 | S32: 2.9562998e+10 | T32: 2.9136856e+10 | U32: JPM | V32: IDDIS | W32: 2.9176666e+10 | Y32: N/A
B33: DEUDAOP | C33: 23/07/2026 | D33: D | E33: D8 | F33: CAFN28 | G33: 1-20 | H33: 24064 | I33: 1032.66 | J33: 1043.8084 | K33: 25118206 | L33: 593 | M33: 0 | N33: 8.5 | O33: 0 | P33: 08/03/2018 | Q33: 08/03/2028 | R33: 46 | S33: 2.9562998e+10 | T33: 2.9136856e+10 | U33: CAF | V33: IDDIS | W33: 2.9176666e+10 | X33: XS1789715064 | Y33: AA
B34: DEUDAOP | C34: 23/07/2026 | D34: D | E34: IM | F34: BPAG28 | G34: 261105 | H34: 500000 | I34: 100.06 | J34: 100.1242 | K34: 50062100 | L34: 104 | M34: 0 | N34: 6.5 | O34: 0 | P34: 09/11/2023 | Q34: 05/11/2026 | R34: 20 | S34: 2.9562998e+10 | T34: 2.9136856e+10 | U34: IPAB | V34: IDDIS | W34: 2.9176666e+10 | X34: MXIMBP0601R3 | Y34: HR AAA
B35: DEUDAOP | C35: 23/07/2026 | D35: D | E35: IM | F35: BPAG28 | G35: 260806 | H35: 2000000 | I35: 100.21 | J35: 100.26789 | K35: 200535772 | L35: 13 | M35: 0 | N35: 6.5 | O35: 0 | P35: 10/08/2023 | Q35: 06/08/2026 | R35: 13 | S35: 2.9562998e+10 | T35: 2.9136856e+10 | U35: IPAB | V35: IDDIS | W35: 2.9176666e+10 | X35: MXIMBP0601Q5 | Y35: HR AAA
B36: DEUDAOP | C36: 23/07/2026 | D36: D | E36: IQ | F36: BPAG91 | G36: 280511 | H36: 1000000 | I36: 100.95 | J36: 101.01847 | K36: 101018471 | L36: 657 | M36: 0 | N36: 6.51 | O36: 0 | P36: 18/05/2023 | Q36: 11/05/2028 | R36: 20 | S36: 2.9562998e+10 | T36: 2.9136856e+10 | U36: IPAB | V36: IDDIS | W36: 2.9176666e+10 | X36: MXIQBP0701P6 | Y36: HR AAA
B37: DEUDAOP | C37: 23/07/2026 | D37: D | E37: IQ | F37: BPAG91 | G37: 280907 | H37: 512000 | I37: 100.39 | J37: 100.44859 | K37: 51429679 | L37: 776 | M37: 0 | N37: 6.48 | O37: 0 | P37: 14/09/2023 | Q37: 07/09/2028 | R37: 48 | S37: 2.9562998e+10 | T37: 2.9136856e+10 | U37: IPAB | V37: IDDIS | W37: 2.9176666e+10 | X37: MXIQBP0701Q4 | Y37: HR AAA
B38: DEUDAOP | C38: 23/07/2026 | D38: D | E38: IQ | F38: BPAG91 | G38: 270909 | H38: 500000 | I38: 100.6 | J38: 100.65327 | K38: 50326638 | L38: 412 | M38: 0 | N38: 6.48 | O38: 0 | P38: 15/09/2022 | Q38: 09/09/2027 | R38: 48 | S38: 2.9562998e+10 | T38: 2.9136856e+10 | U38: IPAB | V38: IDDIS | W38: 2.9176666e+10 | X38: MXIQBP0701N1 | Y38: HR AAA
B39: DEUDAOP | C39: 23/07/2026 | D39: D | E39: IQ | F39: BPAG91 | G39: 270506 | H39: 900000 | I39: 101.35 | J39: 101.39661 | K39: 91256948 | L39: 286 | M39: 0 | N39: 6.74 | O39: 0 | P39: 12/05/2022 | Q39: 06/05/2027 | R39: 13 | S39: 2.9562998e+10 | T39: 2.9136856e+10 | U39: IPAB | V39: IDDIS | W39: 2.9176666e+10 | X39: MXIQBP0701M3 | Y39: HR AAA
B40: DEUDAOP | C40: 23/07/2026 | D40: D | E40: IQ | F40: BPAG91 | G40: 260903 | H40: 400000 | I40: 100.87 | J40: 100.90378 | K40: 40361511 | L40: 41 | M40: 0 | N40: 6.56 | O40: 0 | P40: 09/09/2021 | Q40: 03/09/2026 | R40: 41 | S40: 2.9562998e+10 | T40: 2.9136856e+10 | U40: IPAB | V40: IDDIS | W40: 2.9176666e+10 | X40: MXIQBP0701K7 | Y40: HR AAA
B41: DEUDAOP | C41: 23/07/2026 | D41: D | E41: IQ | F41: BPAG91 | G41: 300516 | H41: 1000000 | I41: 100.39 | J41: 100.45408 | K41: 100454077 | L41: 1392 | M41: 0 | N41: 6.55 | O41: 0 | P41: 22/05/2025 | Q41: 16/05/2030 | R41: 27 | S41: 2.9562998e+10 | T41: 2.9136856e+10 | U41: IPAB | V41: IDDIS | W41: 2.9176666e+10 | X41: MXIQBP0701V4 | Y41: HR AAA
B42: DEUDAOP | C42: 23/07/2026 | D42: D | E42: IQ | F42: BPAG91 | G42: 270107 | H42: 5000000 | I42: 100.22 | J42: 100.22992 | K42: 501149575 | L42: 167 | M42: 0 | N42: 6.5 | O42: 0 | P42: 13/01/2022 | Q42: 07/01/2027 | R42: 76 | S42: 2.9562998e+10 | T42: 2.9136856e+10 | U42: IPAB | V42: IDDIS | W42: 2.9176666e+10 | X42: MXIQBP0701L5 | Y42: HR AAA
B43: DEUDAOP | C43: 23/07/2026 | D43: D | E43: IS | F43: BPA182 | G43: 300328 | H43: 300000 | I43: 101.65 | J43: 101.73772 | K43: 30521318 | L43: 1343 | M43: 0 | N43: 7.15 | O43: 0 | P43: 05/04/2023 | Q43: 28/03/2030 | R43: 69 | S43: 2.9562998e+10 | T43: 2.9136856e+10 | U43: IPAB | V43: IDDIS | W43: 2.9176666e+10 | X43: MXISBP0401L8 | Y43: HR AAA
B44: DEUDAOP | C44: 23/07/2026 | D44: D | E44: IS | F44: BPA182 | G44: 270401 | H44: 400000 | I44: 102.14 | J44: 102.26295 | K44: 40905182 | L44: 251 | M44: 0 | N44: 7.15 | O44: 0 | P44: 08/04/2020 | Q44: 01/04/2027 | R44: 69 | S44: 2.9562998e+10 | T44: 2.9136856e+10 | U44: IPAB | V44: IDDIS | W44: 2.9176666e+10 | X44: MXISBP0401F0 | Y44: HR AAA
... B67: DEUDAOP | C67: 23/07/2026 | D67: D | E67: S | F67: UDIBONO | G67: 290830 | H67: 23549 | I67: 871.18 | J67: 889.41092 | K67: 20944738 | L67: 1133 | M67: 0 | N67: 4 | O67: 0 | P67: 06/03/2025 | Q67: 30/08/2029 | R67: 41 | S67: 2.9562998e+10 | T67: 2.9136856e+10 | U67: GOBMEX | V67: IDDIS | W67: 2.9176666e+10 | X67: MX0SGO0000S3 | Y67: HR AAA
B68: DEUDAOP | C68: 23/07/2026 | D68: D | E68: 0 | F68: UNIFIN | G68: A | H68: 153227 | I68: 1.2 | J68: 1.2 | K68: 183872.4 | L68: 0 | M68: 0 | N68: 0 | O68: 0 | P68: 22/05/2015 | R68: 0 | S68: 2.9562998e+10 | T68: 2.9136856e+10 | U68: UFINCB | V68: IDDIS | W68: 2.9176666e+10 | X68: MX00UN000002 | Y68: NULB
B69: DEUDAOP | C69: 23/07/2026 | D69: D | E69: 91 | F69: ACBE | G69: 26 | H69: 698583 | I69: 100.11 | J69: 100.06257 | K69: 69902010 | L69: 922 | M69: 0 | N69: 6.9 | O69: 0 | P69: 04/02/2026 | Q69: 31/01/2029 | R69: 26 | S69: 2.9562998e+10 | T69: 2.9136856e+10 | U69: ACBE | V69: IDDIS | W69: 2.9176666e+10 | X69: MX91AC1J0063 | Y69: mxAAA
B70: DEUDAOP | C70: 23/07/2026 | D70: D | E70: 91 | F70: AMX | G70: 23-2 | H70: 1209671 | I70: 106.51 | J70: 106.07172 | K70: 1.2831188e+08 | L70: 605 | M70: 0 | N70: 9.35 | O70: 0 | P70: 27/03/2023 | Q70: 20/03/2028 | R70: 59 | S70: 2.9562998e+10 | T70: 2.9136856e+10 | U70: AMX | V70: IDDIS | W70: 2.9176666e+10 | X70: MX91AM0500T5 | Y70: AAA.mx
B71: DEUDAOP | C71: 23/07/2026 | D71: D | E71: 91 | F71: BIMBO | G71: 26-2 | H71: 500000 | I71: 100.59 | J71: 100.4997 | K71: 50249848 | L71: 1288 | M71: 0 | N71: 6.97 | O71: 0 | P71: 06/02/2026 | Q71: 01/02/2030 | R71: 0 | S71: 2.9562998e+10 | T71: 2.9136856e+10 | U71: BIMBO | V71: IDDIS | W71: 2.9176666e+10 | X71: MX91BI0Y00E2 | Y71: mxAAA
B72: DEUDAOP | C72: 23/07/2026 | D72: D | E72: 91 | F72: EDUCA | G72: 26L | H72: 780000 | I72: 100.15 | J72: 100.20632 | K72: 78160931 | L72: 1057 | M72: 0 | N72: 7.9 | O72: 0 | P72: 19/06/2026 | Q72: 15/06/2029 | R72: 21 | S72: 2.9562998e+10 | T72: 2.9136856e+10 | U72: EDUCA | V72: IDDIS | W72: 2.9176666e+10 | X72: MX91ED090054 | Y72: AA+.mx
B73: DEUDAOP | C73: 23/07/2026 | D73: D | E73: 91 | F73: FINN | G73: 18 | H73: 74000 | I73: 104.27 | J73: 105.41582 | K73: 7800770.8 | L73: 558 | M73: 0 | N73: 9.93 | O73: 0 | P73: 14/02/2018 | Q73: 02/02/2028 | R73: 12 | S73: 2.9562998e+10 | T73: 2.9136856e+10 | U73: FINN | V73: IDDIS | W73: 2.9176666e+10 | X73: MX91FI0V0015 | Y73: HR A+
B74: DEUDAOP | C74: 23/07/2026 | D74: D | E74: 91 | F74: FUNO | G74: 25L | H74: 249539 | I74: 100.6 | J74: 100.82985 | K74: 25160981 | L74: 672 | M74: 0 | N74: 7.77 | O74: 0 | P74: 30/05/2025 | Q74: 26/05/2028 | R74: 0 | S74: 2.9562998e+10 | T74: 2.9136856e+10 | U74: FUNO | V74: IDDIS | W74: 2.9176666e+10 | X74: MX91FU0000J9 | Y74: HR AAA
B75: DEUDAOP | C75: 23/07/2026 | D75: D | E75: 91 | F75: GAP | G75: 23-2L | H75: 400000 | I75: 107.6 | J75: 105.87792 | K75: 42351167 | L75: 1333 | M75: 0 | N75: 9.65 | O75: 0 | P75: 27/03/2023 | Q75: 18/03/2030 | R75: 59 | S75: 2.9562998e+10 | T75: 2.9136856e+10 | U75: GAP | V75: IDDIS | W75: 2.9176666e+10 | X75: MX91GA0000F7 | Y75: AAA.mx
B76: DEUDAOP | C76: 23/07/2026 | D76: D | E76: 91 | F76: GAP | G76: 25-2 | H76: 1000000 | I76: 100.54 | J76: 100.60291 | K76: 100602906 | L76: 756 | M76: 0 | N76: 7 | O76: 0 | P76: 22/08/2025 | Q76: 18/08/2028 | R76: 0 | S76: 2.9562998e+10 | T76: 2.9136856e+10 | U76: GAP | V76: IDDIS | W76: 2.9176666e+10 | X76: MX91GA0000L5 | Y76: mxAAA
B77: DEUDAOP | C77: 23/07/2026 | D77: D | E77: 91 | F77: GAP | G77: 25 | H77: 750000 | I77: 100.1 | J77: 100.13166 | K77: 75098745 | L77: 557 | M77: 0 | N77: 7 | O77: 0 | P77: 04/02/2025 | Q77: 01/02/2028 | R77: 25 | S77: 2.9562998e+10 | T77: 2.9136856e+10 | U77: GAP | V77: IDDIS | W77: 2.9176666e+10 | X77: MX91GA0000K7 | Y77: mxAAA
B78: DEUDAOP | C78: 23/07/2026 | D78: D | E78: 91 | F78: GAP | G78: 24 | H78: 1557634 | I78: 101.04 | J78: 101.34919 | K78: 1.5786494e+08 | L78: 1133 | M78: 0 | N78: 7.36 | O78: 0 | P78: 05/09/2024 | Q78: 30/08/2029 | R78: 13 | S78: 2.9562998e+10 | T78: 2.9136856e+10 | U78: GAP | V78: IDDIS | W78: 2.9176666e+10 | X78: MX91GA0000J9 | Y78: mxAAA
B79: DEUDAOP | C79: 23/07/2026 | D79: D | E79: 91 | F79: GAP | G79: 21V | H79: 50000 | I79: 100.12 | J79: 100.13203 | K79: 5006601.5 | L79: 77 | M79: 0 | N79: 7.01 | O79: 0 | P79: 15/10/2021 | Q79: 09/10/2026 | R79: 21 | S79: 2.9562998e+10 | T79: 2.9136856e+10 | U79: GAP | V79: IDDIS | W79: 2.9176666e+10 | X79: MX91GA0000B6 | Y79: AAA.mx
B80: DEUDAOP | C80: 23/07/2026 | D80: D | E80: 91 | F80: GAP | G80: 22 | H80: 530024 | I80: 100.26 | J80: 100.39355 | K80: 53210991 | L80: 230 | M80: 0 | N80: 6.95 | O80: 0 | P80: 17/03/2022 | Q80: 11/03/2027 | R80: 6 | S80: 2.9562998e+10 | T80: 2.9136856e+10 | U80: GAP | V80: IDDIS | W80: 2.9176666e+10 | X80: MX91GA0000C4 | Y80: AAA.mx
... B113: DEUDAOP | C113: 23/07/2026 | D113: D | E113: 94 | F113: VWBANK | G113: 25-2 | H113: 1300000 | I113: 101.57 | J113: 102.87027 | K113: 1.3373135e+08 | L113: 1505 | M113: 0 | N113: 9.25 | O113: 0 | P113: 12/09/2025 | Q113: 06/09/2030 | R113: 49 | S113: 2.9562998e+10 | T113: 2.9136856e+10 | U113: VWBANK | V113: IDDIS | W113: 2.9176666e+10 | X113: MX94VW020062 | Y113: mxAAA
B114: DEUDAOP | C114: 23/07/2026 | D114: D | E114: 94 | F114: BBVAMX | G114: 25D | H114: 5000 | I114: 1829.81 | J114: 1751.9999 | K114: 8759999.7 | L114: 791 | M114: 0 | N114: 4.35 | O114: 0 | P114: 26/09/2025 | Q114: 22/09/2028 | R114: 63 | S114: 2.9562998e+10 | T114: 2.9136856e+10 | U114: BACOMER | V114: IDDIS | W114: 2.9176666e+10 | X114: MX94BB1U00F9 | Y114: mxAAA
B115: DEUDAOP | C115: 23/07/2026 | D115: D | E115: 95 | F115: CFE | G115: 25-3X | H115: 1176316 | I115: 100.57 | J115: 100.17478 | K115: 1.178372e+08 | L115: 801 | M115: 0 | N115: 6.99 | O115: 0 | P115: 06/10/2025 | Q115: 02/10/2028 | R115: 17 | S115: 2.9562998e+10 | T115: 2.9136856e+10 | U115: CFE | V115: IDDIS | W115: 2.9176666e+10 | X115: MX95CF0500Y6 | Y115: mxAAA
B116: DEUDAOP | C116: 23/07/2026 | D116: D | E116: 95 | F116: CFE | G116: 23-3X | H116: 1961336 | I116: 108.78 | J116: 108.24288 | K116: 2.1230066e+08 | L116: 1319 | M116: 0 | N116: 10.88 | O116: 0 | P116: 11/12/2023 | Q116: 04/03/2030 | R116: 136 | S116: 2.9562998e+10 | T116: 2.9136856e+10 | U116: CFE | V116: IDDIS | W116: 2.9176666e+10 | X116: MX95CF0500S8 | Y116: AAA.mx
B117: DEUDAOP | C117: 23/07/2026 | D117: D | E117: 95 | F117: CFE | G117: 23-2X | H117: 840000 | I117: 100.34 | J117: 100.22499 | K117: 84188987 | L117: 136 | M117: 0 | N117: 7.32 | O117: 0 | P117: 11/12/2023 | Q117: 07/12/2026 | R117: 24 | S117: 2.9562998e+10 | T117: 2.9136856e+10 | U117: CFE | V117: IDDIS | W117: 2.9176666e+10 | X117: MX95CF0500R0 | Y117: AAA.mx
B118: DEUDAOP | C118: 23/07/2026 | D118: D | E118: 95 | F118: CFE | G118: 17 | H118: 1466499 | I118: 100.08 | J118: 101.06143 | K118: 1.4820649e+08 | L118: 517 | M118: 0 | N118: 8.18 | O118: 0 | P118: 06/07/2017 | Q118: 23/12/2027 | R118: 153 | S118: 2.9562998e+10 | T118: 2.9136856e+10 | U118: CFE | V118: IDDIS | W118: 2.9176666e+10 | X118: MX95CF050088 | Y118: AAA(mex)
B119: DEUDAOP | C119: 23/07/2026 | D119: D | E119: 95 | F119: CFE | G119: 25X | H119: 1668467 | I119: 101.07 | J119: 100.77808 | K119: 1.681449e+08 | L119: 622 | M119: 0 | N119: 7.16 | O119: 0 | P119: 10/04/2025 | Q119: 06/04/2028 | R119: 6 | S119: 2.9562998e+10 | T119: 2.9136856e+10 | U119: CFE | V119: IDDIS | W119: 2.9176666e+10 | X119: MX95CF0500W0 | Y119: mxAAA
B120: DEUDAOP | C120: 23/07/2026 | D120: D | E120: 95 | F120: FHIPOCB | G120: 17U | H120: 47149 | I120: 234.98 | J120: 241.51952 | K120: 11387404 | L120: 7654 | M120: 0 | N120: 4.13 | O120: 0 | P120: 07/07/2017 | Q120: 08/07/2047 | R120: 38 | S120: 2.9562998e+10 | T120: 2.9136856e+10 | U120: FHIPO | V120: IDDIS | W120: 2.9176666e+10 | X120: MX95FH030002 | Y120: AAA(mex)
B121: DEUDAOP | C121: 23/07/2026 | D121: D | E121: 95 | F121: FNCOT | G121: 24-2 | H121: 300000 | I121: 100.55 | J121: 100.55239 | K121: 30165716 | L121: 448 | M121: 0 | N121: 7.1 | O121: 0 | P121: 18/10/2024 | Q121: 15/10/2027 | R121: 0 | S121: 2.9562998e+10 | T121: 2.9136856e+10 | U121: FONACOT | V121: IDDIS | W121: 2.9176666e+10 | X121: MX95FN0000G1 | Y121: AAA(mex)
B122: DEUDAOP | C122: 23/07/2026 | D122: D | E122: 95 | F122: FNCOT | G122: 25 | H122: 750000 | I122: 100.17 | J122: 100.24589 | K122: 75184419 | L122: 693 | M122: 0 | N122: 7.1 | O122: 0 | P122: 20/06/2025 | Q122: 16/06/2028 | R122: 21 | S122: 2.9562998e+10 | T122: 2.9136856e+10 | U122: FONACOT | V122: IDDIS | W122: 2.9176666e+10 | X122: MX95FN0000H9 | Y122: AAA.mx
B123: DEUDAOP | C123: 23/07/2026 | D123: D | E123: 95 | F123: FNCOT | G123: 25-3 | H123: 2000000 | I123: 101.13 | J123: 102.01469 | K123: 204029370 | L123: 1540 | M123: 0 | N123: 8.94 | O123: 0 | P123: 17/10/2025 | Q123: 11/10/2030 | R123: 84 | S123: 2.9562998e+10 | T123: 2.9136856e+10 | U123: FONACOT | V123: IDDIS | W123: 2.9176666e+10 | X123: MX95FN0000J5 | Y123: AAA.mx
B124: DEUDAOP | C124: 23/07/2026 | D124: D | E124: 95 | F124: FNCOT | G124: 24 | H124: 380000 | I124: 100.35 | J124: 100.33486 | K124: 38127245 | L124: 266 | M124: 0 | N124: 7.14 | O124: 0 | P124: 19/04/2024 | Q124: 16/04/2027 | R124: 14 | S124: 2.9562998e+10 | T124: 2.9136856e+10 | U124: FONACOT | V124: IDDIS | W124: 2.9176666e+10 | X124: MX95FN0000F3 | Y124: AAA(mex)
B125: DEUDAOP | C125: 23/07/2026 | D125: D | E125: 95 | F125: FNCOT | G125: 26-2 | H125: 900000 | I125: 102.32 | J125: 102.43023 | K125: 92187203 | L125: 1729 | M125: 0 | N125: 9.19 | O125: 0 | P125: 24/04/2026 | Q125: 18/04/2031 | R125: 91 | S125: 2.9562998e+10 | T125: 2.9136856e+10 | U125: FONACOT | V125: IDDIS | W125: 2.9176666e+10 | X125: MX95FN0000L1 | Y125: AAA.mx
B126: DEUDAOP | C126: 23/07/2026 | D126: D | E126: 95 | F126: FOVISCB | G126: 17U | H126: 29922 | I126: 196.75 | J126: 202.46956 | K126: 6058294.1 | L126: 7465 | M126: 0 | N126: 3.95 | O126: 0 | P126: 07/08/2017 | Q126: 31/12/2046 | R126: 3 | S126: 2.9562998e+10 | T126: 2.9136856e+10 | U126: FOVISSSTE | V126: IDDIS | W126: 2.9176666e+10 | X126: MX95FO0C0017 | Y126: AAA(mex)
... B162: FONSER1 | C162: 23/07/2026 | D162: D | E162: CD | F162: SHF | G162: 26-2 | H162: 5571055 | I162: 100.43 | J162: 100.43318 | K162: 5.5951876e+08 | L162: 1433 | M162: 0 | N162: 6.78 | O162: 0 | P162: 01/07/2026 | Q162: 26/06/2030 | R162: 5 | S162: 1.1644585e+11 | T162: 1.1626893e+11 | U162: SHF | V162: IDCP | W162: 1.1644191e+11 | X162: MXCDSH0000G4 | Y162: AAA(mex)
B163: FONSER1 | C163: 23/07/2026 | D163: D | E163: CHD | F163: BSANT | G163: 2945000 | H163: 242487 | I163: 17.6 | J163: 17.5269 | K163: 4250046.8 | L163: 0 | M163: 0 | N163: 0 | O163: 0 | P163: 02/02/2021 | R163: 0 | S163: 1.1644585e+11 | T163: 1.1626893e+11 | U163: BANSAN | V163: IDCP | W163: 1.1644191e+11 | Y163: N/A
B164: FONSER1 | C164: 23/07/2026 | D164: D | E164: D8 | F164: CAFN28 | G164: 1-20 | H164: 84281 | I164: 1038.37 | J164: 1043.8084 | K164: 87973219 | L164: 593 | M164: 0 | N164: 8.5 | O164: 0 | P164: 08/03/2018 | Q164: 08/03/2028 | R164: 46 | S164: 1.1644585e+11 | T164: 1.1626893e+11 | U164: CAF | V164: IDCP | W164: 1.1644191e+11 | X164: XS1789715064 | Y164: AA
B165: FONSER1 | C165: 23/07/2026 | D165: D | E165: F | F165: BANSAN | G165: 25160 | H165: 12000000 | I165: 100.3 | J165: 100.2987 | K165: 1203584436 | L165: 12 | M165: 0 | N165: 6.72 | O165: 0 | P165: 06/08/2025 | Q165: 05/08/2026 | R165: 12 | S165: 1.1644585e+11 | T165: 1.1626893e+11 | U165: BANSAN | V165: IDCP | W165: 1.1644191e+11 | X165: MX0FBA013ED0 | Y165: F1+(mex)
B166: FONSER1 | C166: 23/07/2026 | D166: D | E166: F | F166: BANSAN | G166: 25179 | H166: 22400000 | I166: 100.39 | J166: 100.39261 | K166: 2248794352 | L166: 35 | M166: 0 | N166: 6.73 | O166: 0 | P166: 29/08/2025 | Q166: 28/08/2026 | R166: 7 | S166: 1.1644585e+11 | T166: 1.1626893e+11 | U166: BANSAN | V166: IDCP | W166: 1.1644191e+11 | X166: MX0FBA013EV2 | Y166: F1+(mex)
B167: FONSER1 | C167: 23/07/2026 | D167: D | E167: F | F167: BSCTIA | G167: 26005 | H167: 7000000 | I167: 100.06 | J167: 100.05625 | K167: 700393743 | L167: 305 | M167: 0 | N167: 6.74 | O167: 0 | P167: 26/05/2026 | Q167: 25/05/2027 | R167: 25 | S167: 1.1644585e+11 | T167: 1.1626893e+11 | U167: BSCTIA | V167: IDCP | W167: 1.1644191e+11 | X167: MX0FBS000EP1 | Y167: ML A-1.mx
B168: FONSER1 | C168: 23/07/2026 | D168: D | E168: F | F168: BSCTIA | G168: 26008 | H168: 11000000 | I168: 100.02 | J168: 100.01881 | K168: 1100206921 | L168: 335 | M168: 0 | N168: 6.74 | O168: 0 | P168: 25/06/2026 | Q168: 24/06/2027 | R168: 27 | S168: 1.1644585e+11 | T168: 1.1626893e+11 | U168: BSCTIA | V168: IDCP | W168: 1.1644191e+11 | X168: MX0FBS000ES5 | Y168: F1+(mex)
B169: FONSER1 | C169: 23/07/2026 | D169: D | E169: F | F169: CITIMX | G169: 25022 | H169: 4090000 | I169: 100.26 | J169: 100.26372 | K169: 4.1007862e+08 | L169: 14 | M169: 0 | N169: 6.78 | O169: 0 | P169: 08/08/2025 | Q169: 07/08/2026 | R169: 14 | S169: 1.1644585e+11 | T169: 1.1626893e+11 | U169: CITIMX | V169: IDCP | W169: 1.1644191e+11 | X169: MX0FCI1C00L3 | Y169: mxA-1+
B170: FONSER1 | C170: 23/07/2026 | D170: D | E170: F | F170: CITIMX | G170: 26013 | H170: 12700000 | I170: 100.02 | J170: 100.01897 | K170: 1.2702409e+09 | L170: 279 | M170: 0 | N170: 6.79 | O170: 0 | P170: 30/04/2026 | Q170: 29/04/2027 | R170: 27 | S170: 1.1644585e+11 | T170: 1.1626893e+11 | U170: CITIMX | V170: IDCP | W170: 1.1644191e+11 | X170: MX0FCI1C0138 | Y170: mxA-1+
B171: FONSER1 | C171: 23/07/2026 | D171: D | E171: F | F171: CITIMX | G171: 26005 | H171: 15000000 | I171: 100.15 | J171: 100.15052 | K171: 1502257785 | L171: 216 | M171: 0 | N171: 6.77 | O171: 0 | P171: 26/02/2026 | Q171: 25/02/2027 | R171: 20 | S171: 1.1644585e+11 | T171: 1.1626893e+11 | U171: CITIMX | V171: IDCP | W171: 1.1644191e+11 | X171: MX0FCI1C00V2 | Y171: mxA-1+
B172: FONSER1 | C172: 23/07/2026 | D172: D | E172: F | F172: SABADEL | G172: 26007 | H172: 2500000 | I172: 100.04 | J172: 100.03847 | K172: 250096185 | L172: 362 | M172: 0 | N172: 6.9 | O172: 0 | P172: 22/07/2026 | Q172: 21/07/2027 | R172: 16 | S172: 1.1644585e+11 | T172: 1.1626893e+11 | U172: SABADEL | V172: IDCP | W172: 1.1644191e+11 | X172: MX0FSA0S0290 | Y172: mxA-1+
B173: FONSER1 | C173: 23/07/2026 | D173: D | E173: F | F173: SHF | G173: 23002 | H173: 500000 | I173: 100.44 | J173: 100.4364 | K173: 50218198 | L173: 314 | M173: 0 | N173: 6.897 | O173: 0 | P173: 08/06/2023 | Q173: 03/06/2027 | R173: 6 | S173: 1.1644585e+11 | T173: 1.1626893e+11 | U173: SHF | V173: IDCP | W173: 1.1644191e+11 | X173: MX0FSH000486 | Y173: AAA(mex)
B174: FONSER1 | C174: 23/07/2026 | D174: D | E174: I | F174: BANOBRA | G174: 26481 | H174: 300000000 | I174: 0.97 | J174: 0.97666 | K174: 292998000 | L174: 129 | M174: 0 | N174: 6.514 | O174: 0 | P174: 29/05/2026 | Q174: 30/11/2026 | R174: 0 | S174: 1.1644585e+11 | T174: 1.1626893e+11 | U174: BANOBRA | V174: IDCP | W174: 1.1644191e+11 | X174: MX0IBA064WH3 | Y174: mxA-1+
B175: FONSER1 | C175: 23/07/2026 | D175: D | E175: IM | F175: BPAG28 | G175: 270204 | H175: 8197000 | I175: 99.94 | J175: 99.975548 | K175: 8.1949957e+08 | L175: 195 | M175: 0 | N175: 6.5 | O175: 0 | P175: 08/02/2024 | Q175: 04/02/2027 | R175: 27 | S175: 1.1644585e+11 | T175: 1.1626893e+11 | U175: IPAB | V175: IDCP | W175: 1.1644191e+11 | X175: MXIMBP0601S1 | Y175: HR AAA
... B220: FONSER1 | C220: 23/07/2026 | D220: D | E220: S | F220: UDIBONO | G220: 261203 | H220: 1157720 | I220: 881.95 | J220: 884.25062 | K220: 1.0237146e+09 | L220: 132 | M220: 0 | N220: 3 | O220: 0 | P220: 09/12/2021 | Q220: 03/12/2026 | R220: 132 | S220: 1.1644585e+11 | T220: 1.1626893e+11 | U220: GOBMEX | V220: IDCP | W220: 1.1644191e+11 | X220: MX0SGO0000M6 | Y220: HR AAA
B221: FONSER1 | C221: 23/07/2026 | D221: D | E221: 0 | F221: UNIFIN | G221: A | H221: 550942 | I221: 1.2 | J221: 1.2 | K221: 661130.4 | L221: 0 | M221: 0 | N221: 0 | O221: 0 | P221: 22/05/2015 | R221: 0 | S221: 1.1644585e+11 | T221: 1.1626893e+11 | U221: UFINCB | V221: IDCP | W221: 1.1644191e+11 | X221: MX00UN000002 | Y221: NULB
B222: FONSER1 | C222: 23/07/2026 | D222: D | E222: 2 | F222: HICKOK | G222: 90 | H222: 714285 | I222: 0 | J222: 1e-06 | K222: 0.71 | L222: 0 | M222: 0 | N222: 0 | O222: 0 | P222: 08/10/1990 | Q222: 03/11/2050 | R222: 0 | S222: 1.1644585e+11 | T222: 1.1626893e+11 | U222: HICKOK | V222: IDCP | W222: 1.1644191e+11 | X222: MXP4951SAA01 | Y222: No aplica
B223: FONSER1 | C223: 23/07/2026 | D223: D | E223: 91 | F223: AC | G223: 24 | H223: 1500000 | I223: 100.26 | J223: 100.25171 | K223: 150377571 | L223: 182 | M223: 0 | N223: 6.86 | O223: 0 | P223: 26/01/2024 | Q223: 22/01/2027 | R223: 14 | S223: 1.1644585e+11 | T223: 1.1626893e+11 | U223: ARCA | V223: IDCP | W223: 1.1644191e+11 | X223: MX91AC100064 | Y223: AAA(mex)
B224: FONSER1 | C224: 23/07/2026 | D224: D | E224: 91 | F224: ACBE | G224: 26 | H224: 6000000 | I224: 100.06 | J224: 100.06257 | K224: 600375414 | L224: 922 | M224: 0 | N224: 6.9 | O224: 0 | P224: 04/02/2026 | Q224: 31/01/2029 | R224: 26 | S224: 1.1644585e+11 | T224: 1.1626893e+11 | U224: ACBE | V224: IDCP | W224: 1.1644191e+11 | X224: MX91AC1J0063 | Y224: mxAAA
B225: FONSER1 | C225: 23/07/2026 | D225: D | E225: 91 | F225: ACBE | G225: 24L | H225: 849914 | I225: 100.48 | J225: 100.47969 | K225: 85399091 | L225: 311 | M225: 0 | N225: 6.85 | O225: 0 | P225: 08/04/2024 | Q225: 31/05/2027 | R225: 3 | S225: 1.1644585e+11 | T225: 1.1626893e+11 | U225: ACBE | V225: IDCP | W225: 1.1644191e+11 | X225: MX91AC1J0055 | Y225: AAA(mex)
B226: FONSER1 | C226: 23/07/2026 | D226: D | E226: 91 | F226: AMX | G226: 23-2 | H226: 1598372 | I226: 106.72 | J226: 106.07172 | K226: 1.6954207e+08 | L226: 605 | M226: 0 | N226: 9.35 | O226: 0 | P226: 27/03/2023 | Q226: 20/03/2028 | R226: 59 | S226: 1.1644585e+11 | T226: 1.1626893e+11 | U226: AMX | V226: IDCP | W226: 1.1644191e+11 | X226: MX91AM0500T5 | Y226: AAA.mx
B227: FONSER1 | C227: 23/07/2026 | D227: D | E227: 91 | F227: BBPEN | G227: 26X | H227: 2160000 | I227: 100.14 | J227: 100.13602 | K227: 2.1629381e+08 | L227: 1757 | M227: 0 | N227: 7 | O227: 0 | P227: 22/05/2026 | Q227: 16/05/2031 | R227: 21 | S227: 1.1644585e+11 | T227: 1.1626893e+11 | U227: BBPEN | V227: IDCP | W227: 1.1644191e+11 | X227: MX91BB1R0022 | Y227: mxAAA
B228: FONSER1 | C228: 23/07/2026 | D228: D | E228: 91 | F228: BIMBO | G228: 25-2 | H228: 2238000 | I228: 100.43 | J228: 100.31672 | K228: 2.2450882e+08 | L228: 567 | M228: 0 | N228: 6.85 | O228: 0 | P228: 14/02/2025 | Q228: 11/02/2028 | R228: 7 | S228: 1.1644585e+11 | T228: 1.1626893e+11 | U228: BIMBO | V228: IDCP | W228: 1.1644191e+11 | X228: MX91BI0Y00D4 | Y228: mxAAA
B229: FONSER1 | C229: 23/07/2026 | D229: D | E229: 91 | F229: BIMBO | G229: 26-2 | H229: 8000000 | I229: 100.58 | J229: 100.4997 | K229: 803997560 | L229: 1288 | M229: 0 | N229: 6.97 | O229: 0 | P229: 06/02/2026 | Q229: 01/02/2030 | R229: 0 | S229: 1.1644585e+11 | T229: 1.1626893e+11 | U229: BIMBO | V229: IDCP | W229: 1.1644191e+11 | X229: MX91BI0Y00E2 | Y229: mxAAA
B230: FONSER1 | C230: 23/07/2026 | D230: D | E230: 91 | F230: FEMSA | G230: 22L | H230: 25000 | I230: 100.04 | J230: 100.04622 | K230: 2501155.5 | L230: 473 | M230: 0 | N230: 6.85 | O230: 0 | P230: 15/11/2022 | Q230: 09/11/2027 | R230: 25 | S230: 1.1644585e+11 | T230: 1.1626893e+11 | U230: FEMSA | V230: IDCP | W230: 1.1644191e+11 | X230: MX91FE020059 | Y230: AAA(mex)
B231: FONSER1 | C231: 23/07/2026 | D231: D | E231: 91 | F231: FUNO | G231: 25L | H231: 249539 | I231: 100.65 | J231: 100.82985 | K231: 25160981 | L231: 672 | M231: 0 | N231: 7.77 | O231: 0 | P231: 30/05/2025 | Q231: 26/05/2028 | R231: 0 | S231: 1.1644585e+11 | T231: 1.1626893e+11 | U231: FUNO | V231: IDCP | W231: 1.1644191e+11 | X231: MX91FU0000J9 | Y231: HR AAA
B232: FONSER1 | C232: 23/07/2026 | D232: D | E232: 91 | F232: GAP | G232: 25-2 | H232: 500000 | I232: 100.53 | J232: 100.60291 | K232: 50301453 | L232: 756 | M232: 0 | N232: 7 | O232: 0 | P232: 22/08/2025 | Q232: 18/08/2028 | R232: 0 | S232: 1.1644585e+11 | T232: 1.1626893e+11 | U232: GAP | V232: IDCP | W232: 1.1644191e+11 | X232: MX91GA0000L5 | Y232: mxAAA
B233: FONSER1 | C233: 23/07/2026 | D233: D | E233: 91 | F233: GAP | G233: 24 | H233: 2596060 | I233: 101.12 | J233: 101.34919 | K233: 2.6310858e+08 | L233: 1133 | M233: 0 | N233: 7.36 | O233: 0 | P233: 05/09/2024 | Q233: 30/08/2029 | R233: 13 | S233: 1.1644585e+11 | T233: 1.1626893e+11 | U233: GAP | V233: IDCP | W233: 1.1644191e+11 | X233: MX91GA0000J9 | Y233: mxAAA
...

Sheet Dividendos
A1: Posición | B1: SI | D1: =TODAY() -> 46230 | E1: BIVA | F1: COVAF
A2: Fecha Registro | B2: (Todas) | D2: Dividendos | E2: =COUNTA(B6:B99) -> 4 | F2: =COUNTIF(Histórico!B:B,D1) -> 1 | O2: Ruta Archivos:
A3: Ex date/Efectos | B3: (Todas) | F3: =IF(E2=F2,"OK","REVISAR") -> REVISAR | O3: C:\Home Office\Conciliaciones\
A5: Fondo | B5: Portfolio | C5: Tipo de derecho | D5: Posición. | E5: Estatus | F5: ISIN | G5: Fecha Pago | H5: Proporción/importe
A6: FF_FVIA_16 | B6: SVIVE20 | C6: Distribución en efectivo | D6: 46983 | E6: Aplicado | F6: MXFFFV000007 | G6: 27/07/2026 | H6: SERIE(S) '16' CUPON VIGENTE 0 CUPON PAGO 0 A MXN $ 0.3889785940707460
A7: FF_FVIA_16 | B7: SVIVE35 | C7: Distribución en efectivo | D7: 80514 | E7: Aplicado | F7: MXFFFV000007 | G7: 27/07/2026 | H7: SERIE(S) '16' CUPON VIGENTE 0 CUPON PAGO 0 A MXN $ 0.3889785940707460
A8: FF_FVIA_16 | B8: SVIVE50 | C8: Distribución en efectivo | D8: 18838 | E8: Aplicado | F8: MXFFFV000007 | G8: 27/07/2026 | H8: SERIE(S) '16' CUPON VIGENTE 0 CUPON PAGO 0 A MXN $ 0.3889785940707460
A9: 1A_PG_* | B9: SAM-RED | C9: Dividendo en efectivo | D9: 440 | E9: Aplicado | F9: US7427181091 | G9: 17/08/2026 | H9: Option Number: "001" Option Type: "Cash" Default Option: "Yes" Gross Dividend Rate: "1.0885 USD" Option Number: "002" Option Type: "Security" Default Option: "No"

Sheet Histórico
B1: Ex Date | C1: FONDO | D1: EMISORA | E1: SERIE | F1: TV | G1: TIPO DERECHO | I1: FechaPago | J1: MONTO | K1: TITULOS | L1: PROVISION | M1: IMPTO. INTER. | N1: ISR | O1: FechaPago | P1: CUFIN | R1: FONDO | S1: EMISORA | T1: SERIE | U1: TV | V1: MONTO | W1: TITULOS | X1: PROVISION | Y1: IMPTO. INTER. | Z1: ISR | AB1: Monto Bruto | AC1: IMPTO. INTER. | AD1: ISR
B2: 45294 | C2: SAM-SP | D2: CSCO | E2: * | F2: 1A | G2: En efectivo (Moneda Extranjera) | J2: 0.39 | K2: 9460 | L2: 3689.4 | M2: 0.1 | N2: 0.1 | O2: 24/01/2024 | R2: =IF(C2="","",C2) -> SAM-SP | S2: =IF(D2="","",D2) -> CSCO | T2: =IF(E2="","",E2) -> * | U2: =IF(F2="","",F2) -> 1A | V2: 0.39 | W2: 9460 | X2: =V2*W2 -> 3689.4 | Y2: 0.1 | Z2: 0.1 | AB2: =L2-X2 -> 0 | AC2: =M2-Y2 -> 0 | AD2: =N2-Z2 -> 0
B3: 45295 | C3: SAM-RVG | D3: JPM | E3: * | F3: 1A | G3: En efectivo (Moneda Extranjera) | J3: 1.05 | K3: 10760 | L3: 11298 | M3: 0.1 | N3: 0.1 | O3: 31/01/2024 | R3: =IF(C3="","",C3) -> SAM-RVG | S3: =IF(D3="","",D3) -> JPM | T3: =IF(E3="","",E3) -> * | U3: =IF(F3="","",F3) -> 1A | V3: 1.05 | W3: 10760 | X3: =V3*W3 -> 11298 | Y3: 0.1 | Z3: 0.1 | AB3: =L3-X3 -> 0 | AC3: =M3-Y3 -> 0 | AD3: =N3-Z3 -> 0
B4: 45295 | C4: SAM-SP | D4: AXP | E4: * | F4: 1A | G4: En efectivo (Moneda Extranjera) | J4: 0.6 | K4: 5300 | L4: 3180 | M4: 0.1 | N4: 0.1 | O4: 09/02/2024 | R4: =IF(C4="","",C4) -> SAM-SP | S4: =IF(D4="","",D4) -> AXP | T4: =IF(E4="","",E4) -> * | U4: =IF(F4="","",F4) -> 1A | V4: 0.6 | W4: 5300 | X4: =V4*W4 -> 3180 | Y4: 0.1 | Z4: 0.1 | AB4: =L4-X4 -> 0 | AC4: =M4-Y4 -> 0 | AD4: =N4-Z4 -> 0
B5: 45295 | C5: SAM-SP | D5: JPM | E5: * | F5: 1A | G5: En efectivo (Moneda Extranjera) | J5: 1.05 | K5: 6960 | L5: 7308 | M5: 0.1 | N5: 0.1 | O5: 31/01/2024 | R5: =IF(C5="","",C5) -> SAM-SP | S5: =IF(D5="","",D5) -> JPM | T5: =IF(E5="","",E5) -> * | U5: =IF(F5="","",F5) -> 1A | V5: 1.05 | W5: 6960 | X5: =V5*W5 -> 7308 | Y5: 0.1 | Z5: 0.1 | AB5: =L5-X5 -> 0 | AC5: =M5-Y5 -> 0 | AD5: =N5-Z5 -> 0
B6: 45300 | C6: SAMEME2 | D6: INTU | E6: * | F6: 1A | G6: En efectivo (Moneda Extranjera) | J6: 0.9 | K6: 3800 | L6: 3420 | M6: 0.1 | N6: 0.1 | O6: 45309 | R6: =IF(C6="","",C6) -> SAMEME2 | S6: =IF(D6="","",D6) -> INTU | T6: =IF(E6="","",E6) -> * | U6: =IF(F6="","",F6) -> 1A | V6: 0.9 | W6: 3800 | X6: =V6*W6 -> 3420 | Y6: 0.1 | Z6: 0.1 | AB6: =L6-X6 -> 0 | AC6: =M6-Y6 -> 0 | AD6: =N6-Z6 -> 0
B7: 45300 | C7: EURO-EQ | D7: IBE | E7: N | F7: 1A | G7: En efectivo (Moneda Extranjera) | J7: 0.202 | K7: 16718 | L7: 3377.04 | M7: 0.1 | N7: 0.1 | O7: 45322 | R7: =IF(C7="","",C7) -> EURO-EQ | S7: =IF(D7="","",D7) -> IBE | T7: =IF(E7="","",E7) -> N | U7: =IF(F7="","",F7) -> 1A | V7: 0.202 | W7: 16718 | X7: =V7*W7 -> 3377.036 | Y7: 0.1 | Z7: 0.1 | AB7: =L7-X7 -> 0.004 | AC7: =M7-Y7 -> 0 | AD7: =N7-Z7 -> 0
B8: 45301 | C8: SAM-AF | D8: GRUMA | E8: B | F8: 1 | G8: En efectivo (Moneda Nacional) | J8: 1.35 | K8: 65200 | L8: 88020 | M8: 0 | N8: 0.1 | O8: 12/01/2024 | R8: =IF(C8="","",C8) -> SAM-AF | S8: =IF(D8="","",D8) -> GRUMA | T8: =IF(E8="","",E8) -> B | U8: =IF(F8="","",F8) -> 1 | V8: 1.35 | W8: 65200 | X8: =V8*W8 -> 88020 | Y8: 0 | Z8: 0.1 | AB8: =L8-X8 -> 0 | AC8: =M8-Y8 -> 0 | AD8: =N8-Z8 -> 0
B9: 45301 | C9: SAM-ESG | D9: GRUMA | E9: B | F9: 1 | G9: En efectivo (Moneda Nacional) | J9: 1.35 | K9: 128000 | L9: 172800 | M9: 0 | N9: 0.1 | O9: 12/01/2024 | R9: =IF(C9="","",C9) -> SAM-ESG | S9: =IF(D9="","",D9) -> GRUMA | T9: =IF(E9="","",E9) -> B | U9: =IF(F9="","",F9) -> 1 | V9: 1.35 | W9: 128000 | X9: =V9*W9 -> 172800 | Y9: 0 | Z9: 0.1 | AB9: =L9-X9 -> 0 | AC9: =M9-Y9 -> 0 | AD9: =N9-Z9 -> 0
B10: 45301 | C10: ST&ER-C | D10: GRUMA | E10: B | F10: 1 | G10: En efectivo (Moneda Nacional) | J10: 1.35 | K10: 26100 | L10: 35235 | M10: 0 | N10: 0.1 | O10: 12/01/2024 | R10: =IF(C10="","",C10) -> ST&ER-C | S10: =IF(D10="","",D10) -> GRUMA | T10: =IF(E10="","",E10) -> B | U10: =IF(F10="","",F10) -> 1 | V10: 1.35 | W10: 26100 | X10: =V10*W10 -> 35235 | Y10: 0 | Z10: 0.1 | AB10: =L10-X10 -> 0 | AC10: =M10-Y10 -> 0 | AD10: =N10-Z10 -> 0
B11: 45301 | C11: STER-OP | D11: GRUMA | E11: B | F11: 1 | G11: En efectivo (Moneda Nacional) | J11: 1.35 | K11: 769000 | L11: 1038150 | M11: 0 | N11: 0.1 | O11: 12/01/2024 | R11: =IF(C11="","",C11) -> STER-OP | S11: =IF(D11="","",D11) -> GRUMA | T11: =IF(E11="","",E11) -> B | U11: =IF(F11="","",F11) -> 1 | V11: 1.35 | W11: 769000 | X11: =V11*W11 -> 1038150 | Y11: 0 | Z11: 0.1 | AB11: =L11-X11 -> 0 | AC11: =M11-Y11 -> 0 | AD11: =N11-Z11 -> 0
B12: 45301 | C12: USA-EQ | D12: ORCL | E12: * | F12: 1A | G12: En efectivo (Moneda Extranjera) | J12: 0.4 | K12: 109490 | L12: 43796 | M12: 0.1 | N12: 0.1 | O12: 25/01/2024 | R12: =IF(C12="","",C12) -> USA-EQ | S12: =IF(D12="","",D12) -> ORCL | T12: =IF(E12="","",E12) -> * | U12: =IF(F12="","",F12) -> 1A | V12: 0.4 | W12: 109490 | X12: =V12*W12 -> 43796 | Y12: 0.1 | Z12: 0.1 | AB12: =L12-X12 -> 0 | AC12: =M12-Y12 -> 0 | AD12: =N12-Z12 -> 0
B13: 45302 | C13: SAMEMEC | D13: AHT | E13: N | F13: 1A | G13: En efectivo (Moneda Extranjera) | J13: 0.1575 | K13: 52350 | L13: 8245.13 | M13: 0.1 | N13: 0.1 | O13: 08/02/2024 | R13: =IF(C13="","",C13) -> SAMEMEC | S13: =IF(D13="","",D13) -> AHT | T13: =IF(E13="","",E13) -> N | U13: =IF(F13="","",F13) -> 1A | V13: 0.1575 | W13: 52350 | X13: =V13*W13 -> 8245.125 | Y13: 0.1 | Z13: 0.1 | AB13: =L13-X13 -> 0.005 | AC13: =M13-Y13 -> 0 | AD13: =N13-Z13 -> 0
B14: 45302 | C14: SAMEME1 | D14: AHT | E14: N | F14: 1A | G14: En efectivo (Moneda Extranjera) | J14: 0.1575 | K14: 60309 | L14: 9498.67 | M14: 0.1 | N14: 0.1 | O14: 08/02/2024 | R14: =IF(C14="","",C14) -> SAMEME1 | S14: =IF(D14="","",D14) -> AHT | T14: =IF(E14="","",E14) -> N | U14: =IF(F14="","",F14) -> 1A | V14: 0.1575 | W14: 60309 | X14: =V14*W14 -> 9498.6675 | Y14: 0.1 | Z14: 0.1 | AB14: =L14-X14 -> 0.0025 | AC14: =M14-Y14 -> 0 | AD14: =N14-Z14 -> 0
B15: 45302 | C15: SAMEME2 | D15: AHT | E15: N | F15: 1A | G15: En efectivo (Moneda Extranjera) | J15: 0.1575 | K15: 31864 | L15: 5018.58 | M15: 0.1 | N15: 0.1 | O15: 08/02/2024 | R15: =IF(C15="","",C15) -> SAMEME2 | S15: =IF(D15="","",D15) -> AHT | T15: =IF(E15="","",E15) -> N | U15: =IF(F15="","",F15) -> 1A | V15: 0.1575 | W15: 31864 | X15: =V15*W15 -> 5018.58 | Y15: 0.1 | Z15: 0.1 | AB15: =L15-X15 -> 0 | AC15: =M15-Y15 -> 0 | AD15: =N15-Z15 -> 0
B16: 45302 | C16: SAM-AF | D16: VESTA | E16: * | F16: 1 | G16: En efectivo (Moneda Extranjera) | J16: 0.017157 | K16: 165000 | L16: 2830.87 | M16: 0 | N16: 0.1 | O16: 15/01/2024 | R16: =IF(C16="","",C16) -> SAM-AF | S16: =IF(D16="","",D16) -> VESTA | T16: =IF(E16="","",E16) -> * | U16: =IF(F16="","",F16) -> 1 | V16: 0.017157 | W16: 165000 | X16: =V16*W16 -> 2830.905 | Y16: 0 | Z16: 0.1 | AB16: =L16-X16 -> -0.035 | AC16: =M16-Y16 -> 0 | AD16: =N16-Z16 -> 0
B17: 45302 | C17: SAM-ESG | D17: VESTA | E17: * | F17: 1 | G17: En efectivo (Moneda Extranjera) | J17: 0.017157 | K17: 458000 | L17: 7857.8 | M17: 0 | N17: 0.1 | O17: 15/01/2024 | R17: =IF(C17="","",C17) -> SAM-ESG | S17: =IF(D17="","",D17) -> VESTA | T17: =IF(E17="","",E17) -> * | U17: =IF(F17="","",F17) -> 1 | V17: 0.017157 | W17: 458000 | X17: =V17*W17 -> 7857.906 | Y17: 0 | Z17: 0.1 | AB17: =L17-X17 -> -0.106 | AC17: =M17-Y17 -> 0 | AD17: =N17-Z17 -> 0
B18: 45302 | C18: ST&ER-C | D18: VESTA | E18: * | F18: 1 | G18: En efectivo (Moneda Extranjera) | J18: 0.017157 | K18: 118763 | L18: 2037.59 | M18: 0 | N18: 0.1 | O18: 15/01/2024 | R18: =IF(C18="","",C18) -> ST&ER-C | S18: =IF(D18="","",D18) -> VESTA | T18: =IF(E18="","",E18) -> * | U18: =IF(F18="","",F18) -> 1 | V18: 0.017157 | W18: 118763 | X18: =V18*W18 -> 2037.6168 | Y18: 0 | Z18: 0.1 | AB18: =L18-X18 -> -0.026791 | AC18: =M18-Y18 -> 0 | AD18: =N18-Z18 -> 0
B19: 45302 | C19: STER-OP | D19: VESTA | E19: * | F19: 1 | G19: En efectivo (Moneda Extranjera) | J19: 0.017157 | K19: 3625000 | L19: 62193.27 | M19: 0 | N19: 0.1 | O19: 15/01/2024 | R19: =IF(C19="","",C19) -> STER-OP | S19: =IF(D19="","",D19) -> VESTA | T19: =IF(E19="","",E19) -> * | U19: =IF(F19="","",F19) -> 1 | V19: 0.017157 | W19: 3625000 | X19: =V19*W19 -> 62194.125 | Y19: 0 | Z19: 0.1 | AB19: =L19-X19 -> -0.855 | AC19: =M19-Y19 -> 0 | AD19: =N19-Z19 -> 0
B20: 45303 | C20: SAM-RVG | D20: ABBV | E20: * | F20: 1A | G20: En efectivo (Moneda Extranjera) | J20: 1.55 | K20: 4110 | L20: 6370.5 | M20: 0.1 | N20: 0.1 | O20: 45337 | R20: =IF(C20="","",C20) -> SAM-RVG | S20: =IF(D20="","",D20) -> ABBV | T20: =IF(E20="","",E20) -> * | U20: =IF(F20="","",F20) -> 1A | V20: 1.55 | W20: 4110 | X20: =V20*W20 -> 6370.5 | Y20: 0.1 | Z20: 0.1 | AB20: =L20-X20 -> 0 | AC20: =M20-Y20 -> 0 | AD20: =N20-Z20 -> 0
B21: 45308 | C21: SAM-RVG | D21: ACN | E21: N | F21: 1A | G21: En efectivo (Moneda Extranjera) | J21: 1.29 | K21: 2030 | L21: 2618.7 | M21: 0.25 | N21: 0.1 | O21: 45337 | R21: =IF(C21="","",C21) -> SAM-RVG | S21: =IF(D21="","",D21) -> ACN | T21: =IF(E21="","",E21) -> N | U21: =IF(F21="","",F21) -> 1A | V21: 1.29 | W21: 2030 | X21: =V21*W21 -> 2618.7 | Y21: 0.25 | Z21: 0.1 | AB21: =L21-X21 -> 0 | AC21: =M21-Y21 -> 0 | AD21: =N21-Z21 -> 0
B22: 45308 | C22: SAM-SP | D22: ACN | E22: N | F22: 1A | G22: En efectivo (Moneda Extranjera) | J22: 1.29 | K22: 1390 | L22: 1793.1 | M22: 0.25 | N22: 0.1 | O22: 45337 | R22: =IF(C22="","",C22) -> SAM-SP | S22: =IF(D22="","",D22) -> ACN | T22: =IF(E22="","",E22) -> N | U22: =IF(F22="","",F22) -> 1A | V22: 1.29 | W22: 1390 | X22: =V22*W22 -> 1793.1 | Y22: 0.25 | Z22: 0.1 | AB22: =L22-X22 -> 0 | AC22: =M22-Y22 -> 0 | AD22: =N22-Z22 -> 0
B23: 45309 | C23: SAMEMEC | D23: RVTY | E23: * | F23: 1A | G23: En efectivo (Moneda Extranjera) | J23: 0.07 | K23: 19530 | L23: 1367.1 | M23: 0.1 | N23: 0.1 | O23: 09/02/2024 | R23: =IF(C23="","",C23) -> SAMEMEC | S23: =IF(D23="","",D23) -> RVTY | T23: =IF(E23="","",E23) -> * | U23: =IF(F23="","",F23) -> 1A | V23: 0.07 | W23: 19530 | X23: =V23*W23 -> 1367.1 | Y23: 0.1 | Z23: 0.1 | AB23: =L23-X23 -> 0 | AC23: =M23-Y23 -> 0 | AD23: =N23-Z23 -> 0
B24: 45309 | C24: SAMEME1 | D24: RVTY | E24: * | F24: 1A | G24: En efectivo (Moneda Extranjera) | J24: 0.07 | K24: 13671 | L24: 956.97 | M24: 0.1 | N24: 0.1 | O24: 09/02/2024 | R24: =IF(C24="","",C24) -> SAMEME1 | S24: =IF(D24="","",D24) -> RVTY | T24: =IF(E24="","",E24) -> * | U24: =IF(F24="","",F24) -> 1A | V24: 0.07 | W24: 13671 | X24: =V24*W24 -> 956.97 | Y24: 0.1 | Z24: 0.1 | AB24: =L24-X24 -> 0 | AC24: =M24-Y24 -> 0 | AD24: =N24-Z24 -> 0
B25: 45309 | C25: SAM-SP | D25: PG | E25: * | F25: 1A | G25: En efectivo (Moneda Extranjera) | J25: 0.9407 | K25: 8950 | L25: 8419.27 | M25: 0.1 | N25: 0.1 | O25: 15/02/2024 | R25: =IF(C25="","",C25) -> SAM-SP | S25: =IF(D25="","",D25) -> PG | T25: =IF(E25="","",E25) -> * | U25: =IF(F25="","",F25) -> 1A | V25: 0.9407 | W25: 8950 | X25: =V25*W25 -> 8419.265 | Y25: 0.1 | Z25: 0.1 | AB25: =L25-X25 -> 0.005 | AC25: =M25-Y25 -> 0 | AD25: =N25-Z25 -> 0
B26: 45310 | C26: SAMEMEC | D26: CVS | E26: * | F26: 1A | G26: En efectivo (Moneda Extranjera) | J26: 0.665 | K26: 22040 | L26: 14656.6 | M26: 0.1 | N26: 0.1 | O26: 45323 | R26: =IF(C26="","",C26) -> SAMEMEC | S26: =IF(D26="","",D26) -> CVS | T26: =IF(E26="","",E26) -> * | U26: =IF(F26="","",F26) -> 1A | V26: 0.665 | W26: 22040 | X26: =V26*W26 -> 14656.6 | Y26: 0.1 | Z26: 0.1 | AB26: =L26-X26 -> 0 | AC26: =M26-Y26 -> 0 | AD26: =N26-Z26 -> 0
B27: 45310 | C27: SAMEME1 | D27: CVS | E27: * | F27: 1A | G27: En efectivo (Moneda Extranjera) | J27: 0.665 | K27: 30469 | L27: 20261.89 | M27: 0.1 | N27: 0.1 | O27: 45323 | R27: =IF(C27="","",C27) -> SAMEME1 | S27: =IF(D27="","",D27) -> CVS | T27: =IF(E27="","",E27) -> * | U27: =IF(F27="","",F27) -> 1A | V27: 0.665 | W27: 30469 | X27: =V27*W27 -> 20261.885 | Y27: 0.1 | Z27: 0.1 | AB27: =L27-X27 -> 0.005 | AC27: =M27-Y27 -> 0 | AD27: =N27-Z27 -> 0
B28: 45310 | C28: SAM-RED | D28: CL | E28: * | F28: 1A | G28: En efectivo (Moneda Extranjera) | J28: 0.48 | K28: 1770 | L28: 849.6 | M28: 0.1 | N28: 0.1 | O28: 45337 | R28: =IF(C28="","",C28) -> SAM-RED | S28: =IF(D28="","",D28) -> CL | T28: =IF(E28="","",E28) -> * | U28: =IF(F28="","",F28) -> 1A | V28: 0.48 | W28: 1770 | X28: =V28*W28 -> 849.6 | Y28: 0.1 | Z28: 0.1 | AB28: =L28-X28 -> 0 | AC28: =M28-Y28 -> 0 | AD28: =N28-Z28 -> 0
B29: 45310 | C29: SAM-SP | D29: CAT | E29: * | F29: 1A | G29: En efectivo (Moneda Extranjera) | J29: 1.3 | K29: 4120 | L29: 5356 | M29: 0.1 | N29: 0.1 | O29: 45342 | R29: =IF(C29="","",C29) -> SAM-SP | S29: =IF(D29="","",D29) -> CAT | T29: =IF(E29="","",E29) -> * | U29: =IF(F29="","",F29) -> 1A | V29: 1.3 | W29: 4120 | X29: =V29*W29 -> 5356 | Y29: 0.1 | Z29: 0.1 | AB29: =L29-X29 -> 0 | AC29: =M29-Y29 -> 0 | AD29: =N29-Z29 -> 0
B30: 45315 | C30: SAM-RVG | D30: MMC | E30: * | F30: 1A | G30: En efectivo (Moneda Extranjera) | J30: 0.71 | K30: 7410 | L30: 5261.1 | M30: 0.1 | N30: 0.1 | O30: 45337 | R30: =IF(C30="","",C30) -> SAM-RVG | S30: =IF(D30="","",D30) -> MMC | T30: =IF(E30="","",E30) -> * | U30: =IF(F30="","",F30) -> 1A | V30: 0.71 | W30: 7410 | X30: =V30*W30 -> 5261.1 | Y30: 0.1 | Z30: 0.1 | AB30: =L30-X30 -> 0 | AC30: =M30-Y30 -> 0 | AD30: =N30-Z30 -> 0
B31: 45316 | C31: SAM-SP | D31: PFE | E31: * | F31: 1A | G31: En efectivo (Moneda Extranjera) | J31: 0.42 | K31: 23690 | L31: 9949.8 | M31: 0.1 | N31: 0.1 | O31: 45352 | R31: =IF(C31="","",C31) -> SAM-SP | S31: =IF(D31="","",D31) -> PFE | T31: =IF(E31="","",E31) -> * | U31: =IF(F31="","",F31) -> 1A | V31: 0.42 | W31: 23690 | X31: =V31*W31 -> 9949.8 | Y31: 0.1 | Z31: 0.1 | AB31: =L31-X31 -> 0 | AC31: =M31-Y31 -> 0 | AD31: =N31-Z31 -> 0
B32: 45316 | C32: SAMUSCP | D32: USFR | E32: * | F32: 1I | G32: En efectivo (Moneda Extranjera) | J32: 0.227 | K32: 74352 | L32: 16877.9 | M32: 0.1 | N32: 0.1 | O32: 45321 | R32: =IF(C32="","",C32) -> SAMUSCP | S32: =IF(D32="","",D32) -> USFR | T32: =IF(E32="","",E32) -> * | U32: =IF(F32="","",F32) -> 1I | V32: 0.227 | W32: 74352 | X32: =V32*W32 -> 16877.904 | Y32: 0.1 | Z32: 0.1 | AB32: =L32-X32 -> -0.004 | AC32: =M32-Y32 -> 0 | AD32: =N32-Z32 -> 0
B33: 45317 | C33: SAM-AF | D33: FIBRAMQ | E33: 12 | F33: CF | G33: Distribución del Resultado Fiscal de FIBRAS | J33: 0.525 | K33: 157000 | L33: 82425 | M33: 0 | N33: 0.3 | O33: 45321 | R33: =IF(C33="","",C33) -> SAM-AF | S33: =IF(D33="","",D33) -> FIBRAMQ | T33: =IF(E33="","",E33) -> 12 | U33: =IF(F33="","",F33) -> CF | V33: 0.525 | W33: 157000 | X33: =V33*W33 -> 82425 | Y33: 0 | Z33: 0.3 | AB33: =L33-X33 -> 0 | AC33: =M33-Y33 -> 0 | AD33: =N33-Z33 -> 0
B34: 45317 | C34: SAM-ESG | D34: FIBRAMQ | E34: 12 | F34: CF | G34: Distribución del Resultado Fiscal de FIBRAS | J34: 0.525 | K34: 271000 | L34: 142275 | M34: 0 | N34: 0.3 | O34: 45321 | R34: =IF(C34="","",C34) -> SAM-ESG | S34: =IF(D34="","",D34) -> FIBRAMQ | T34: =IF(E34="","",E34) -> 12 | U34: =IF(F34="","",F34) -> CF | V34: 0.525 | W34: 271000 | X34: =V34*W34 -> 142275 | Y34: 0 | Z34: 0.3 | AB34: =L34-X34 -> 0 | AC34: =M34-Y34 -> 0 | AD34: =N34-Z34 -> 0
B35: 45320 | C35: ELIGE-C | D35: NAFTRAC | E35: ISHRS | F35: 1B | G35: En efectivo (Moneda Nacional) | J35: 0.003297 | K35: 315420 | L35: 1039.98 | M35: 0 | N35: 0 | O35: 45322 | R35: =IF(C35="","",C35) -> ELIGE-C | S35: =IF(D35="","",D35) -> NAFTRAC | T35: =IF(E35="","",E35) -> ISHRS | U35: =IF(F35="","",F35) -> 1B | V35: 0.003297 | W35: 315420 | X35: =V35*W35 -> 1039.9397 | Y35: 0 | Z35: 0 | AB35: =L35-X35 -> 0.04026 | AC35: =M35-Y35 -> 0 | AD35: =N35-Z35 -> 0
B36: 45320 | C36: ELIGE-C | D36: NAFTRAC | E36: ISHRS | F36: 1B | G36: En efectivo (Moneda Nacional) | J36: 0.009109 | K36: 315420 | L36: 2873.3 | M36: 0 | N36: 0.1 | O36: 45322 | R36: =IF(C36="","",C36) -> ELIGE-C | S36: =IF(D36="","",D36) -> NAFTRAC | T36: =IF(E36="","",E36) -> ISHRS | U36: =IF(F36="","",F36) -> 1B | V36: 0.009109 | W36: 315420 | X36: =V36*W36 -> 2873.1608 | Y36: 0 | Z36: 0.1 | AB36: =L36-X36 -> 0.13922 | AC36: =M36-Y36 -> 0 | AD36: =N36-Z36 -> 0
B37: 45320 | C37: ELIGE-C | D37: NAFTRAC | E37: ISHRS | F37: 1B | G37: En efectivo (Moneda Nacional) | J37: 0.00753 | K37: 315420 | L37: 2375.24 | M37: 0 | N37: 0.1 | O37: 45322 | R37: =IF(C37="","",C37) -> ELIGE-C | S37: =IF(D37="","",D37) -> NAFTRAC | T37: =IF(E37="","",E37) -> ISHRS | U37: =IF(F37="","",F37) -> 1B | V37: 0.00753 | W37: 315420 | X37: =V37*W37 -> 2375.1126 | Y37: 0 | Z37: 0.1 | AB37: =L37-X37 -> 0.1274 | AC37: =M37-Y37 -> 0 | AD37: =N37-Z37 -> 0
B38: 45320 | C38: ELIGE-P | D38: NAFTRAC | E38: ISHRS | F38: 1B | G38: En efectivo (Moneda Nacional) | J38: 0.00753 | K38: 5450875 | L38: 41047.33 | M38: 0 | N38: 0.1 | O38: 45322 | R38: =IF(C38="","",C38) -> ELIGE-P | S38: =IF(D38="","",D38) -> NAFTRAC | T38: =IF(E38="","",E38) -> ISHRS | U38: =IF(F38="","",F38) -> 1B | V38: 0.00753 | W38: 5450875 | X38: =V38*W38 -> 41045.089 | Y38: 0 | Z38: 0.1 | AB38: =L38-X38 -> 2.24125 | AC38: =M38-Y38 -> 0 | AD38: =N38-Z38 -> 0
B39: 45320 | C39: ELIGE-P | D39: NAFTRAC | E39: ISHRS | F39: 1B | G39: En efectivo (Moneda Nacional) | J39: 0.003297 | K39: 5450875 | L39: 17972.31 | M39: 0 | N39: 0 | O39: 45322 | R39: =IF(C39="","",C39) -> ELIGE-P | S39: =IF(D39="","",D39) -> NAFTRAC | T39: =IF(E39="","",E39) -> ISHRS | U39: =IF(F39="","",F39) -> 1B | V39: 0.003297 | W39: 5450875 | X39: =V39*W39 -> 17971.535 | Y39: 0 | Z39: 0 | AB39: =L39-X39 -> 0.775125 | AC39: =M39-Y39 -> 0 | AD39: =N39-Z39 -> 0
B40: 45320 | C40: ELIGE-P | D40: NAFTRAC | E40: ISHRS | F40: 1B | G40: En efectivo (Moneda Nacional) | J40: 0.009109 | K40: 5450875 | L40: 49654.36 | M40: 0 | N40: 0.1 | O40: 45322 | R40: =IF(C40="","",C40) -> ELIGE-P | S40: =IF(D40="","",D40) -> NAFTRAC | T40: =IF(E40="","",E40) -> ISHRS | U40: =IF(F40="","",F40) -> 1B | V40: 0.009109 | W40: 5450875 | X40: =V40*W40 -> 49652.02 | Y40: 0 | Z40: 0.1 | AB40: =L40-X40 -> 2.339625 | AC40: =M40-Y40 -> 0 | AD40: =N40-Z40 -> 0
B41: 45320 | C41: SAM-AP | D41: NAFTRAC | E41: ISHRS | F41: 1B | G41: En efectivo (Moneda Nacional) | J41: 0.009109 | K41: 30000 | L41: 273.28 | M41: 0 | N41: 0.1 | O41: 45322 | R41: =IF(C41="","",C41) -> SAM-AP | S41: =IF(D41="","",D41) -> NAFTRAC | T41: =IF(E41="","",E41) -> ISHRS | U41: =IF(F41="","",F41) -> 1B | V41: 0.009109 | W41: 30000 | X41: =V41*W41 -> 273.27 | Y41: 0 | Z41: 0.1 | AB41: =L41-X41 -> 0.01 | AC41: =M41-Y41 -> 0 | AD41: =N41-Z41 -> 0
B42: 45320 | C42: SAM-AP | D42: NAFTRAC | E42: ISHRS | F42: 1B | G42: En efectivo (Moneda Nacional) | J42: 0.00753 | K42: 30000 | L42: 225.91 | M42: 0 | N42: 0.1 | O42: 45322 | R42: =IF(C42="","",C42) -> SAM-AP | S42: =IF(D42="","",D42) -> NAFTRAC | T42: =IF(E42="","",E42) -> ISHRS | U42: =IF(F42="","",F42) -> 1B | V42: 0.00753 | W42: 30000 | X42: =V42*W42 -> 225.9 | Y42: 0 | Z42: 0.1 | AB42: =L42-X42 -> 0.01 | AC42: =M42-Y42 -> 0 | AD42: =N42-Z42 -> 0
B43: 45320 | C43: SAM-AP | D43: NAFTRAC | E43: ISHRS | F43: 1B | G43: En efectivo (Moneda Nacional) | J43: 0.003297 | K43: 30000 | L43: 98.91 | M43: 0 | N43: 0 | O43: 45322 | R43: =IF(C43="","",C43) -> SAM-AP | S43: =IF(D43="","",D43) -> NAFTRAC | T43: =IF(E43="","",E43) -> ISHRS | U43: =IF(F43="","",F43) -> 1B | V43: 0.003297 | W43: 30000 | X43: =V43*W43 -> 98.91 | Y43: 0 | Z43: 0 | AB43: =L43-X43 -> 0 | AC43: =M43-Y43 -> 0 | AD43: =N43-Z43 -> 0
B44: 45321 | C44: SAM-AF | D44: FIBRAPL | E44: 14 | F44: CF | G44: Distribución del Resultado Fiscal de FIBRAS | J44: 0.612846 | K44: 85000 | L44: 52091.94 | M44: 0 | N44: 0.3 | O44: 01/02/2024 | R44: =IF(C44="","",C44) -> SAM-AF | S44: =IF(D44="","",D44) -> FIBRAPL | T44: =IF(E44="","",E44) -> 14 | U44: =IF(F44="","",F44) -> CF | V44: 0.612846 | W44: 85000 | X44: =V44*W44 -> 52091.91 | Y44: 0 | Z44: 0.3 | AB44: =L44-X44 -> 0.03 | AC44: =M44-Y44 -> 0 | AD44: =N44-Z44 -> 0
B45: 45321 | C45: SAM-ESG | D45: FIBRAPL | E45: 14 | F45: CF | G45: Distribución del Resultado Fiscal de FIBRAS | J45: 0.612846 | K45: 182000 | L45: 111538.03 | M45: 0 | N45: 0.3 | O45: 01/02/2024 | R45: =IF(C45="","",C45) -> SAM-ESG | S45: =IF(D45="","",D45) -> FIBRAPL | T45: =IF(E45="","",E45) -> 14 | U45: =IF(F45="","",F45) -> CF | V45: 0.612846 | W45: 182000 | X45: =V45*W45 -> 111537.97 | Y45: 0 | Z45: 0.3 | AB45: =L45-X45 -> 0.058 | AC45: =M45-Y45 -> 0 | AD45: =N45-Z45 -> 0
B46: 45321 | C46: SAM-SP | D46: MS | E46: * | F46: 1A | G46: En efectivo (Moneda Extranjera) | J46: 0.85 | K46: 9480 | L46: 8058 | M46: 0.1 | N46: 0.1 | O46: 15/02/2024 | R46: =IF(C46="","",C46) -> SAM-SP | S46: =IF(D46="","",D46) -> MS | T46: =IF(E46="","",E46) -> * | U46: =IF(F46="","",F46) -> 1A | V46: 0.85 | W46: 9480 | X46: =V46*W46 -> 8058 | Y46: 0.1 | Z46: 0.1 | AB46: =L46-X46 -> 0 | AC46: =M46-Y46 -> 0 | AD46: =N46-Z46 -> 0
B47: 45321 | C47: SAM-SP | D47: WST | E47: * | F47: 1A | G47: En efectivo (Moneda Extranjera) | J47: 0.2 | K47: 1000 | L47: 200 | M47: 0.1 | N47: 0.1 | O47: 01/02/2024 | R47: =IF(C47="","",C47) -> SAM-SP | S47: =IF(D47="","",D47) -> WST | T47: =IF(E47="","",E47) -> * | U47: =IF(F47="","",F47) -> 1A | V47: 0.2 | W47: 1000 | X47: =V47*W47 -> 200 | Y47: 0.1 | Z47: 0.1 | AB47: =L47-X47 -> 0 | AC47: =M47-Y47 -> 0 | AD47: =N47-Z47 -> 0
B48: 45321 | C48: SAM-RED | D48: QIA | E48: N | F48: 1A | G48: Reembolso (Moneda Extranjera) | J48: 1.28 | K48: 3060 | L48: 3916.8 | M48: 0 | N48: 0 | R48: =IF(C48="","",C48) -> SAM-RED | S48: =IF(D48="","",D48) -> QIA | T48: =IF(E48="","",E48) -> N | U48: =IF(F48="","",F48) -> 1A | V48: 1.28 | W48: 3060 | X48: =V48*W48 -> 3916.8 | Y48: 0 | Z48: 0 | AB48: =L48-X48 -> 0 | AC48: =M48-Y48 -> 0 | AD48: =N48-Z48 -> 0
B49: 45321 | C49: SAM-AF | D49: FIBRAPL | E49: 14 | F49: CF | G49: Distribución del Resultado Fiscal de FIBRAS | O49: 01/02/2024 | R49: =IF(C49="","",C49) -> SAM-AF | S49: =IF(D49="","",D49) -> FIBRAPL | T49: =IF(E49="","",E49) -> 14 | U49: =IF(F49="","",F49) -> CF | X49: =V49*W49 -> 0 | AB49: =L49-X49 -> 0 | AC49: =M49-Y49 -> 0 | AD49: =N49-Z49 -> 0 | AE49: Dividendo en Acciones
B50: 45321 | C50: SAM-ESG | D50: FIBRAPL | E50: 14 | F50: CF | G50: Distribución del Resultado Fiscal de FIBRAS | O50: 01/02/2024 | R50: =IF(C50="","",C50) -> SAM-ESG | S50: =IF(D50="","",D50) -> FIBRAPL | T50: =IF(E50="","",E50) -> 14 | U50: =IF(F50="","",F50) -> CF | X50: =V50*W50 -> 0 | AB50: =L50-X50 -> 0 | AC50: =M50-Y50 -> 0 | AD50: =N50-Z50 -> 0 | AE50: Dividendo en Acciones
B51: 45323 | C51: SAM-RVG | D51: COST | E51: * | F51: 1A | G51: En efectivo (Moneda Extranjera) | J51: 1.02 | K51: 2230 | L51: 2274.6 | M51: 0.1 | N51: 0.1 | O51: 45338 | R51: =IF(C51="","",C51) -> SAM-RVG | S51: =IF(D51="","",D51) -> COST | T51: =IF(E51="","",E51) -> * | U51: =IF(F51="","",F51) -> 1A | V51: 1.02 | W51: 2230 | X51: =V51*W51 -> 2274.6 | Y51: 0.1 | Z51: 0.1 | AB51: =L51-X51 -> 0 | AC51: =M51-Y51 -> 0 | AD51: =N51-Z51 -> 0
B52: 45323 | C52: SAMUSCP | D52: BIL | E52: * | F52: 1I | G52: En efectivo (Moneda Extranjera) | J52: 0.406361 | K52: 323400 | L52: 131417.15 | M52: 0.1 | N52: 0.1 | O52: 45329 | R52: =IF(C52="","",C52) -> SAMUSCP | S52: =IF(D52="","",D52) -> BIL | T52: =IF(E52="","",E52) -> * | U52: =IF(F52="","",F52) -> 1I | V52: 0.406361 | W52: 323400 | X52: =V52*W52 -> 131417.15 | Y52: 0.1 | Z52: 0.1 | AB52: =L52-X52 -> 0.0026 | AC52: =M52-Y52 -> 0 | AD52: =N52-Z52 -> 0
B53: 45323 | C53: SAMUSCP | D53: SHV | E53: * | F53: 1I | G53: En efectivo (Moneda Extranjera) | J53: 0.47335 | K53: 58169 | L53: 27534.3 | M53: 0.1 | N53: 0.1 | O53: 45329 | R53: =IF(C53="","",C53) -> SAMUSCP | S53: =IF(D53="","",D53) -> SHV | T53: =IF(E53="","",E53) -> * | U53: =IF(F53="","",F53) -> 1I | V53: 0.47335 | W53: 58169 | X53: =V53*W53 -> 27534.296 | Y53: 0.1 | Z53: 0.1 | AB53: =L53-X53 -> 0.00385 | AC53: =M53-Y53 -> 0 | AD53: =N53-Z53 -> 0
B54: 45323 | C54: STERUSD | D54: BIL | E54: * | F54: 1I | G54: En efectivo (Moneda Extranjera) | J54: 0.406361 | K54: 278452 | L54: 113152.03 | M54: 0.1 | N54: 0.1 | O54: 45329 | R54: =IF(C54="","",C54) -> STERUSD | S54: =IF(D54="","",D54) -> BIL | T54: =IF(E54="","",E54) -> * | U54: =IF(F54="","",F54) -> 1I | V54: 0.406361 | W54: 278452 | X54: =V54*W54 -> 113152.03 | Y54: 0.1 | Z54: 0.1 | AB54: =L54-X54 -> -0.003172 | AC54: =M54-Y54 -> 0 | AD54: =N54-Z54 -> 0
B55: 45323 | C55: STERUSD | D55: IEF | E55: * | F55: 1I | G55: En efectivo (Moneda Extranjera) | J55: 0.235883 | K55: 344325 | L55: 81220.41 | M55: 0.1 | N55: 0.1 | O55: 45329 | R55: =IF(C55="","",C55) -> STERUSD | S55: =IF(D55="","",D55) -> IEF | T55: =IF(E55="","",E55) -> * | U55: =IF(F55="","",F55) -> 1I | V55: 0.235883 | W55: 344325 | X55: =V55*W55 -> 81220.414 | Y55: 0.1 | Z55: 0.1 | AB55: =L55-X55 -> -0.003975 | AC55: =M55-Y55 -> 0 | AD55: =N55-Z55 -> 0
B56: 45323 | C56: STERUSD | D56: IEI | E56: * | F56: 1I | G56: En efectivo (Moneda Extranjera) | J56: 0.28656 | K56: 310397 | L56: 88947.36 | M56: 0.1 | N56: 0.1 | O56: 45329 | R56: =IF(C56="","",C56) -> STERUSD | S56: =IF(D56="","",D56) -> IEI | T56: =IF(E56="","",E56) -> * | U56: =IF(F56="","",F56) -> 1I | V56: 0.28656 | W56: 310397 | X56: =V56*W56 -> 88947.364 | Y56: 0.1 | Z56: 0.1 | AB56: =L56-X56 -> -0.00432 | AC56: =M56-Y56 -> 0 | AD56: =N56-Z56 -> 0
B57: 45323 | C57: STERUSD | D57: SHV | E57: * | F57: 1I | G57: En efectivo (Moneda Extranjera) | J57: 0.47335 | K57: 216984 | L57: 102709.38 | M57: 0.1 | N57: 0.1 | O57: 45329 | R57: =IF(C57="","",C57) -> STERUSD | S57: =IF(D57="","",D57) -> SHV | T57: =IF(E57="","",E57) -> * | U57: =IF(F57="","",F57) -> 1I | V57: 0.47335 | W57: 216984 | X57: =V57*W57 -> 102709.38 | Y57: 0.1 | Z57: 0.1 | AB57: =L57-X57 -> 0.0036 | AC57: =M57-Y57 -> 0 | AD57: =N57-Z57 -> 0
B58: 45323 | C58: STRIVS1 | D58: IEF | E58: * | F58: 1I | G58: En efectivo (Moneda Extranjera) | J58: 0.235883 | K58: 7370 | L58: 1738.46 | M58: 0.1 | N58: 0.1 | O58: 45329 | R58: =IF(C58="","",C58) -> STRIVS1 | S58: =IF(D58="","",D58) -> IEF | T58: =IF(E58="","",E58) -> * | U58: =IF(F58="","",F58) -> 1I | V58: 0.235883 | W58: 7370 | X58: =V58*W58 -> 1738.4577 | Y58: 0.1 | Z58: 0.1 | AB58: =L58-X58 -> 0.00229 | AC58: =M58-Y58 -> 0 | AD58: =N58-Z58 -> 0
B59: 45323 | C59: XPERT-B | D59: SHV | E59: * | F59: 1I | G59: En efectivo (Moneda Extranjera) | J59: 0.47335 | K59: 25420 | L59: 12032.56 | M59: 0.1 | N59: 0.1 | O59: 45329 | R59: =IF(C59="","",C59) -> XPERT-B | S59: =IF(D59="","",D59) -> SHV | T59: =IF(E59="","",E59) -> * | U59: =IF(F59="","",F59) -> 1I | V59: 0.47335 | W59: 25420 | X59: =V59*W59 -> 12032.557 | Y59: 0.1 | Z59: 0.1 | AB59: =L59-X59 -> 0.003 | AC59: =M59-Y59 -> 0 | AD59: =N59-Z59 -> 0
B60: 45323 | C60: XPERT-C | D60: SHV | E60: * | F60: 1I | G60: En efectivo (Moneda Extranjera) | J60: 0.47335 | K60: 9900 | L60: 4686.17 | M60: 0.1 | N60: 0.1 | O60: 45329 | R60: =IF(C60="","",C60) -> XPERT-C | S60: =IF(D60="","",D60) -> SHV | T60: =IF(E60="","",E60) -> * | U60: =IF(F60="","",F60) -> 1I | V60: 0.47335 | W60: 9900 | X60: =V60*W60 -> 4686.165 | Y60: 0.1 | Z60: 0.1 | AB60: =L60-X60 -> 0.005 | AC60: =M60-Y60 -> 0 | AD60: =N60-Z60 -> 0
B61: 45323 | C61: XPERT-D | D61: SHV | E61: * | F61: 1I | G61: En efectivo (Moneda Extranjera) | J61: 0.47335 | K61: 12360 | L61: 5850.61 | M61: 0.1 | N61: 0.1 | O61: 45329 | R61: =IF(C61="","",C61) -> XPERT-D | S61: =IF(D61="","",D61) -> SHV | T61: =IF(E61="","",E61) -> * | U61: =IF(F61="","",F61) -> 1I | V61: 0.47335 | W61: 12360 | X61: =V61*W61 -> 5850.606 | Y61: 0.1 | Z61: 0.1 | AB61: =L61-X61 -> 0.004 | AC61: =M61-Y61 -> 0 | AD61: =N61-Z61 -> 0
B62: 45324 | C62: SVIVE20 | D62: FORION | E62: 20 | F62: FF | G62: Distribución de Reembolso FIBRAS | J62: 10.073225 | K62: 3010 | L62: 30320.41 | M62: 0 | N62: 0 | O62: 45329 | R62: =IF(C62="","",C62) -> SVIVE20 | S62: =IF(D62="","",D62) -> FORION | T62: =IF(E62="","",E62) -> 20 | U62: =IF(F62="","",F62) -> FF | V62: 10.073225 | W62: 3010 | X62: =V62*W62 -> 30320.407 | Y62: 0 | Z62: 0 | AB62: =L62-X62 -> 0.00275 | AC62: =M62-Y62 -> 0 | AD62: =N62-Z62 -> 0
B63: 45324 | C63: SVIVE35 | D63: FORION | E63: 20 | F63: FF | G63: Distribución de Reembolso FIBRAS | J63: 10.073225 | K63: 5910 | L63: 59532.76 | M63: 0 | N63: 0 | O63: 45329 | R63: =IF(C63="","",C63) -> SVIVE35 | S63: =IF(D63="","",D63) -> FORION | T63: =IF(E63="","",E63) -> 20 | U63: =IF(F63="","",F63) -> FF | V63: 10.073225 | W63: 5910 | X63: =V63*W63 -> 59532.76 | Y63: 0 | Z63: 0 | AB63: =L63-X63 -> 0.00025 | AC63: =M63-Y63 -> 0 | AD63: =N63-Z63 -> 0
B64: 45324 | C64: SVIVE50 | D64: FORION | E64: 20 | F64: FF | G64: Distribución de Reembolso FIBRAS | J64: 10.073225 | K64: 3430 | L64: 34551.16 | M64: 0 | N64: 0 | O64: 45329 | R64: =IF(C64="","",C64) -> SVIVE50 | S64: =IF(D64="","",D64) -> FORION | T64: =IF(E64="","",E64) -> 20 | U64: =IF(F64="","",F64) -> FF | V64: 10.073225 | W64: 3430 | X64: =V64*W64 -> 34551.162 | Y64: 0 | Z64: 0 | AB64: =L64-X64 -> -0.00175 | AC64: =M64-Y64 -> 0 | AD64: =N64-Z64 -> 0
B65: 45324 | C65: SAM-SP | D65: C | E65: * | F65: 1A | G65: En efectivo (Moneda Extranjera) | J65: 0.53 | K65: 17300 | L65: 9169 | M65: 0.1 | N65: 0.1 | O65: 23/02/2024 | R65: =IF(C65="","",C65) -> SAM-SP | S65: =IF(D65="","",D65) -> C | T65: =IF(E65="","",E65) -> * | U65: =IF(F65="","",F65) -> 1A | V65: 0.53 | W65: 17300 | X65: =V65*W65 -> 9169 | Y65: 0.1 | Z65: 0.1 | AB65: =L65-X65 -> 0 | AC65: =M65-Y65 -> 0 | AD65: =N65-Z65 -> 0
B66: 45328 | C66: SAMEMEC | D66: ASML1 | E66: N | F66: 1ASP | G66: En efectivo (Moneda Extranjera) | J66: 1.55556 | K66: 2030 | L66: 3157.79 | M66: 0.15 | N66: 0.1 | O66: 14/02/2024 | R66: =IF(C66="","",C66) -> SAMEMEC | S66: =IF(D66="","",D66) -> ASML1 | T66: =IF(E66="","",E66) -> N | U66: =IF(F66="","",F66) -> 1ASP | V66: 1.55556 | W66: 2030 | X66: =V66*W66 -> 3157.7868 | Y66: 0.15 | Z66: 0.1 | AB66: =L66-X66 -> 0.0032 | AC66: =M66-Y66 -> 0 | AD66: =N66-Z66 -> 0
B67: 45328 | C67: SAMEME1 | D67: ASML | E67: N | F67: 1ASP | G67: En efectivo (Moneda Extranjera) | J67: 1.45 | K67: 1857 | L67: 2692.65 | M67: 0.15 | N67: 0.1 | O67: 14/02/2024 | R67: =IF(C67="","",C67) -> SAMEME1 | S67: =IF(D67="","",D67) -> ASML | T67: =IF(E67="","",E67) -> N | U67: =IF(F67="","",F67) -> 1ASP | V67: 1.45 | W67: 1857 | X67: =V67*W67 -> 2692.65 | Y67: 0.15 | Z67: 0.1 | AB67: =L67-X67 -> 0 | AC67: =M67-Y67 -> 0 | AD67: =N67-Z67 -> 0
B68: 45328 | C68: SAMEME2 | D68: ASML | E68: N | F68: 1ASP | G68: En efectivo (Moneda Extranjera) | J68: 1.45 | K68: 9447 | L68: 13698.15 | M68: 0.15 | N68: 0.1 | O68: 14/02/2024 | R68: =IF(C68="","",C68) -> SAMEME2 | S68: =IF(D68="","",D68) -> ASML | T68: =IF(E68="","",E68) -> N | U68: =IF(F68="","",F68) -> 1ASP | V68: 1.45 | W68: 9447 | X68: =V68*W68 -> 13698.15 | Y68: 0.15 | Z68: 0.1 | AB68: =L68-X68 -> 0 | AC68: =M68-Y68 -> 0 | AD68: =N68-Z68 -> 0
B69: 45328 | C69: SAM-RVG | D69: LNG | E69: * | F69: 1ASP | G69: En efectivo (Moneda Extranjera) | J69: 0.435 | K69: 7720 | L69: 3358.2 | M69: 0.1 | N69: 0.1 | O69: 14/02/2024 | R69: =IF(C69="","",C69) -> SAM-RVG | S69: =IF(D69="","",D69) -> LNG | T69: =IF(E69="","",E69) -> * | U69: =IF(F69="","",F69) -> 1ASP | V69: 0.435 | W69: 7720 | X69: =V69*W69 -> 3358.2 | Y69: 0.1 | Z69: 0.1 | AB69: =L69-X69 -> 0 | AC69: =M69-Y69 -> 0 | AD69: =N69-Z69 -> 0
B70: 45328 | C70: SAM-RVG | D70: SLB | E70: N | F70: 1ASP | G70: En efectivo (Moneda Extranjera) | J70: 0.275 | K70: 20020 | L70: 5505.5 | M70: 0.1 | N70: 0.1 | O70: 13/02/2024 | R70: =IF(C70="","",C70) -> SAM-RVG | S70: =IF(D70="","",D70) -> SLB | T70: =IF(E70="","",E70) -> N | U70: =IF(F70="","",F70) -> 1ASP | V70: 0.275 | W70: 20020 | X70: =V70*W70 -> 5505.5 | Y70: 0.1 | Z70: 0.1 | AB70: =L70-X70 -> 0 | AC70: =M70-Y70 -> 0 | AD70: =N70-Z70 -> 0
B71: 45328 | C71: SAM-SP | D71: DHI | E71: * | F71: 1ASP | G71: En efectivo (Moneda Extranjera) | J71: 0.3 | K71: 2400 | L71: 720 | M71: 0.1 | N71: 0.1 | O71: 01/03/2024 | R71: =IF(C71="","",C71) -> SAM-SP | S71: =IF(D71="","",D71) -> DHI | T71: =IF(E71="","",E71) -> * | U71: =IF(F71="","",F71) -> 1ASP | V71: 0.3 | W71: 2400 | X71: =V71*W71 -> 720 | Y71: 0.1 | Z71: 0.1 | AB71: =L71-X71 -> 0 | AC71: =M71-Y71 -> 0 | AD71: =N71-Z71 -> 0
B72: 45328 | C72: SAM-SP | D72: INTC | E72: * | F72: 1ASP | G72: En efectivo (Moneda Extranjera) | J72: 0.125 | K72: 11930 | L72: 1491.25 | M72: 0.1 | N72: 0.1 | O72: 01/03/2024 | R72: =IF(C72="","",C72) -> SAM-SP | S72: =IF(D72="","",D72) -> INTC | T72: =IF(E72="","",E72) -> * | U72: =IF(F72="","",F72) -> 1ASP | V72: 0.125 | W72: 11930 | X72: =V72*W72 -> 1491.25 | Y72: 0.1 | Z72: 0.1 | AB72: =L72-X72 -> 0 | AC72: =M72-Y72 -> 0 | AD72: =N72-Z72 -> 0
B73: 45328 | C73: STERNDQ | D73: ASML1 | E73: N | F73: 1ASP | G73: En efectivo (Moneda Extranjera) | J73: 1.55556 | K73: 1100 | L73: 1711.12 | M73: 0.15 | N73: 0.1 | O73: 23/02/2024 | R73: =IF(C73="","",C73) -> STERNDQ | S73: =IF(D73="","",D73) -> ASML1 | T73: =IF(E73="","",E73) -> N | U73: =IF(F73="","",F73) -> 1ASP | V73: 1.55556 | W73: 1100 | X73: =V73*W73 -> 1711.116 | Y73: 0.15 | Z73: 0.1 | AB73: =L73-X73 -> 0.004 | AC73: =M73-Y73 -> 0 | AD73: =N73-Z73 -> 0
B74: 45328 | C74: STERNDQ | D74: INTC | E74: * | F74: 1ASP | G74: En efectivo (Moneda Extranjera) | J74: 0.125 | K74: 11300 | L74: 1412.5 | M74: 0.1 | N74: 0.1 | O74: 04/04/2024 | R74: =IF(C74="","",C74) -> STERNDQ | S74: =IF(D74="","",D74) -> INTC | T74: =IF(E74="","",E74) -> * | U74: =IF(F74="","",F74) -> 1ASP | V74: 0.125 | W74: 11300 | X74: =V74*W74 -> 1412.5 | Y74: 0.1 | Z74: 0.1 | AB74: =L74-X74 -> 0 | AC74: =M74-Y74 -> 0 | AD74: =N74-Z74 -> 0
B75: 45329 | C75: SAMEME1 | D75: RMD | E75: * | F75: 1ASP | G75: En efectivo (Moneda Extranjera) | J75: 0.48 | K75: 5320 | L75: 2553.6 | M75: 0.1 | N75: 0.1 | O75: 14/03/2024 | R75: =IF(C75="","",C75) -> SAMEME1 | S75: =IF(D75="","",D75) -> RMD | T75: =IF(E75="","",E75) -> * | U75: =IF(F75="","",F75) -> 1ASP | V75: 0.48 | W75: 5320 | X75: =V75*W75 -> 2553.6 | Y75: 0.1 | Z75: 0.1 | AB75: =L75-X75 -> 0 | AC75: =M75-Y75 -> 0 | AD75: =N75-Z75 -> 0
B76: 45330 | C76: SAM-RED | D76: IBM | E76: * | F76: 1ASP | G76: En efectivo (Moneda Extranjera) | J76: 1.66 | K76: 730 | L76: 1211.8 | M76: 0.1 | N76: 0.1 | O76: 09/03/2024 | R76: =IF(C76="","",C76) -> SAM-RED | S76: =IF(D76="","",D76) -> IBM | T76: =IF(E76="","",E76) -> * | U76: =IF(F76="","",F76) -> 1ASP | V76: 1.66 | W76: 730 | X76: =V76*W76 -> 1211.8 | Y76: 0.1 | Z76: 0.1 | AB76: =L76-X76 -> 0 | AC76: =M76-Y76 -> 0 | AD76: =N76-Z76 -> 0
... B87: 45335 | C87: SAM-SP | D87: XOM | E87: * | F87: 1ASP | G87: En efectivo (Moneda Extranjera) | J87: 0.95 | K87: 10230 | L87: 9718.5 | M87: 0.1 | N87: 0.1 | O87: 11/03/2024 | R87: =IF(C87="","",C87) -> SAM-SP | S87: =IF(D87="","",D87) -> XOM | T87: =IF(E87="","",E87) -> * | U87: =IF(F87="","",F87) -> 1ASP | V87: 0.95 | W87: 10230 | X87: =V87*W87 -> 9718.5 | Y87: 0.1 | Z87: 0.1 | AB87: =L87-X87 -> 0 | AC87: =M87-Y87 -> 0 | AD87: =N87-Z87 -> 0
B88: 45336 | C88: SAM-RVG | D88: LLY | E88: * | F88: 1ASP | G88: En efectivo (Moneda Extranjera) | J88: 1.3 | K88: 2230 | L88: 2899 | M88: 0.1 | N88: 0.1 | O88: 45359 | R88: =IF(C88="","",C88) -> SAM-RVG | S88: =IF(D88="","",D88) -> LLY | T88: =IF(E88="","",E88) -> * | U88: =IF(F88="","",F88) -> 1ASP | V88: 1.3 | W88: 2230 | X88: =V88*W88 -> 2899 | Y88: 0.1 | Z88: 0.1 | AB88: =L88-X88 -> 0 | AC88: =M88-Y88 -> 0 | AD88: =N88-Z88 -> 0
B89: 45336 | C89: SAM-SP | D89: LLY | E89: * | F89: 1ASP | G89: En efectivo (Moneda Extranjera) | J89: 1.3 | K89: 2490 | L89: 3237 | M89: 0.1 | N89: 0.1 | O89: 45359 | R89: =IF(C89="","",C89) -> SAM-SP | S89: =IF(D89="","",D89) -> LLY | T89: =IF(E89="","",E89) -> * | U89: =IF(F89="","",F89) -> 1ASP | V89: 1.3 | W89: 2490 | X89: =V89*W89 -> 3237 | Y89: 0.1 | Z89: 0.1 | AB89: =L89-X89 -> 0 | AC89: =M89-Y89 -> 0 | AD89: =N89-Z89 -> 0
B90: 45336 | C90: SAMEMEC | D90: MSFT | E90: * | F90: 1ASP | G90: En efectivo (Moneda Extranjera) | J90: 0.75 | K90: 6540 | L90: 4905 | M90: 0.1 | N90: 0.1 | O90: 45365 | R90: =IF(C90="","",C90) -> SAMEMEC | S90: =IF(D90="","",D90) -> MSFT | T90: =IF(E90="","",E90) -> * | U90: =IF(F90="","",F90) -> 1ASP | V90: 0.75 | W90: 6540 | X90: =V90*W90 -> 4905 | Y90: 0.1 | Z90: 0.1 | AB90: =L90-X90 -> 0 | AC90: =M90-Y90 -> 0 | AD90: =N90-Z90 -> 0
B91: 45336 | C91: SAMEME1 | D91: MSFT | E91: * | F91: 1ASP | G91: En efectivo (Moneda Extranjera) | J91: 0.75 | K91: 12668 | L91: 9501 | M91: 0.1 | N91: 0.1 | O91: 45365 | R91: =IF(C91="","",C91) -> SAMEME1 | S91: =IF(D91="","",D91) -> MSFT | T91: =IF(E91="","",E91) -> * | U91: =IF(F91="","",F91) -> 1ASP | V91: 0.75 | W91: 12668 | X91: =V91*W91 -> 9501 | Y91: 0.1 | Z91: 0.1 | AB91: =L91-X91 -> 0 | AC91: =M91-Y91 -> 0 | AD91: =N91-Z91 -> 0
B92: 45336 | C92: SAMEME2 | D92: MSFT | E92: * | F92: 1ASP | G92: En efectivo (Moneda Extranjera) | J92: 0.75 | K92: 30395 | L92: 22796.25 | M92: 0.1 | N92: 0.1 | O92: 45365 | R92: =IF(C92="","",C92) -> SAMEME2 | S92: =IF(D92="","",D92) -> MSFT | T92: =IF(E92="","",E92) -> * | U92: =IF(F92="","",F92) -> 1ASP | V92: 0.75 | W92: 30395 | X92: =V92*W92 -> 22796.25 | Y92: 0.1 | Z92: 0.1 | AB92: =L92-X92 -> 0 | AC92: =M92-Y92 -> 0 | AD92: =N92-Z92 -> 0
B93: 45336 | C93: SAM-RVG | D93: MSFT | E93: * | F93: 1ASP | G93: En efectivo (Moneda Extranjera) | J93: 0.75 | K93: 9950 | L93: 7462.5 | M93: 0.1 | N93: 0.1 | O93: 45365 | R93: =IF(C93="","",C93) -> SAM-RVG | S93: =IF(D93="","",D93) -> MSFT | T93: =IF(E93="","",E93) -> * | U93: =IF(F93="","",F93) -> 1ASP | V93: 0.75 | W93: 9950 | X93: =V93*W93 -> 7462.5 | Y93: 0.1 | Z93: 0.1 | AB93: =L93-X93 -> 0 | AC93: =M93-Y93 -> 0 | AD93: =N93-Z93 -> 0
B94: 45336 | C94: SAM-SP | D94: MSFT | E94: * | F94: 1ASP | G94: En efectivo (Moneda Extranjera) | J94: 0.75 | K94: 15750 | L94: 11812.5 | M94: 0.1 | N94: 0.1 | O94: 45365 | R94: =IF(C94="","",C94) -> SAM-SP | S94: =IF(D94="","",D94) -> MSFT | T94: =IF(E94="","",E94) -> * | U94: =IF(F94="","",F94) -> 1ASP | V94: 0.75 | W94: 15750 | X94: =V94*W94 -> 11812.5 | Y94: 0.1 | Z94: 0.1 | AB94: =L94-X94 -> 0 | AC94: =M94-Y94 -> 0 | AD94: =N94-Z94 -> 0
B95: 45336 | C95: USA-EQ | D95: MSFT | E95: * | F95: 1ASP | G95: En efectivo (Moneda Extranjera) | J95: 0.75 | K95: 35840 | L95: 26880 | M95: 0.1 | N95: 0.1 | O95: 45365 | R95: =IF(C95="","",C95) -> USA-EQ | S95: =IF(D95="","",D95) -> MSFT | T95: =IF(E95="","",E95) -> * | U95: =IF(F95="","",F95) -> 1ASP | V95: 0.75 | W95: 35840 | X95: =V95*W95 -> 26880 | Y95: 0.1 | Z95: 0.1 | AB95: =L95-X95 -> 0 | AC95: =M95-Y95 -> 0 | AD95: =N95-Z95 -> 0
B96: 45337 | C96: SAM-RED | D96: AMGN | E96: * | F96: 1ASP | G96: En efectivo (Moneda Extranjera) | J96: 2.25 | K96: 460 | L96: 1035 | M96: 0.1 | N96: 0.1 | O96: 07/03/2024 | R96: =IF(C96="","",C96) -> SAM-RED | S96: =IF(D96="","",D96) -> AMGN | T96: =IF(E96="","",E96) -> * | U96: =IF(F96="","",F96) -> 1ASP | V96: 2.25 | W96: 460 | X96: =V96*W96 -> 1035 | Y96: 0.1 | Z96: 0.1 | AB96: =L96-X96 -> 0 | AC96: =M96-Y96 -> 0 | AD96: =N96-Z96 -> 0
B97: 45337 | C97: SAM-SP | D97: AMGN | E97: * | F97: 1ASP | G97: En efectivo (Moneda Extranjera) | J97: 2.25 | K97: 3790 | L97: 8527.5 | M97: 0.1 | N97: 0.1 | O97: 07/03/2024 | R97: =IF(C97="","",C97) -> SAM-SP | S97: =IF(D97="","",D97) -> AMGN | T97: =IF(E97="","",E97) -> * | U97: =IF(F97="","",F97) -> 1ASP | V97: 2.25 | W97: 3790 | X97: =V97*W97 -> 8527.5 | Y97: 0.1 | Z97: 0.1 | AB97: =L97-X97 -> 0 | AC97: =M97-Y97 -> 0 | AD97: =N97-Z97 -> 0
B98: 45337 | C98: SAM-SP | D98: CVX | E98: * | F98: 1ASP | G98: En efectivo (Moneda Extranjera) | J98: 1.63 | K98: 2670 | L98: 4352.1 | M98: 0.1 | N98: 0.1 | O98: 11/03/2024 | R98: =IF(C98="","",C98) -> SAM-SP | S98: =IF(D98="","",D98) -> CVX | T98: =IF(E98="","",E98) -> * | U98: =IF(F98="","",F98) -> 1ASP | V98: 1.63 | W98: 2670 | X98: =V98*W98 -> 4352.1 | Y98: 0.1 | Z98: 0.1 | AB98: =L98-X98 -> 0 | AC98: =M98-Y98 -> 0 | AD98: =N98-Z98 -> 0
B99: 45337 | C99: SAMEME2 | D99: MSCI | E99: * | F99: 1ASP | G99: En efectivo (Moneda Extranjera) | J99: 1.6 | K99: 3395 | L99: 5432 | M99: 0.1 | N99: 0.1 | O99: 29/02/2024 | R99: =IF(C99="","",C99) -> SAMEME2 | S99: =IF(D99="","",D99) -> MSCI | T99: =IF(E99="","",E99) -> * | U99: =IF(F99="","",F99) -> 1ASP | V99: 1.6 | W99: 3395 | X99: =V99*W99 -> 5432 | Y99: 0.1 | Z99: 0.1 | AB99: =L99-X99 -> 0 | AC99: =M99-Y99 -> 0 | AD99: =N99-Z99 -> 0
B100: 45337 | C100: SAMEMEC | D100: SHEL1 | E100: N | F100: 1ASP | G100: En efectivo (Moneda Extranjera) | J100: 0.688 | K100: 48330 | L100: 33251.04 | M100: 0.1 | N100: 0.1 | O100: 25/03/2024 | R100: =IF(C100="","",C100) -> SAMEMEC | S100: =IF(D100="","",D100) -> SHEL1 | T100: =IF(E100="","",E100) -> N | U100: =IF(F100="","",F100) -> 1ASP | V100: 0.688 | W100: 48330 | X100: =V100*W100 -> 33251.04 | Y100: 0.1 | Z100: 0.1 | AB100: =L100-X100 -> 0 | AC100: =M100-Y100 -> 0 | AD100: =N100-Z100 -> 0
B101: 45337 | C101: SAMEME1 | D101: SHEL1 | E101: N | F101: 1ASP | G101: En efectivo (Moneda Extranjera) | J101: 0.688 | K101: 58188 | L101: 40033.34 | M101: 0.1 | N101: 0.1 | O101: 25/03/2024 | R101: =IF(C101="","",C101) -> SAMEME1 | S101: =IF(D101="","",D101) -> SHEL1 | T101: =IF(E101="","",E101) -> N | U101: =IF(F101="","",F101) -> 1ASP | V101: 0.688 | W101: 58188 | X101: =V101*W101 -> 40033.344 | Y101: 0.1 | Z101: 0.1 | AB101: =L101-X101 -> -0.004 | AC101: =M101-Y101 -> 0 | AD101: =N101-Z101 -> 0
B102: 45342 | C102: USA-EQ | D102: YUM | E102: * | F102: 1ASP | G102: En efectivo (Moneda Extranjera) | J102: 0.67 | K102: 22870 | L102: 15322.9 | M102: 0.1 | N102: 0.1 | O102: 08/03/2024 | R102: =IF(C102="","",C102) -> USA-EQ | S102: =IF(D102="","",D102) -> YUM | T102: =IF(E102="","",E102) -> * | U102: =IF(F102="","",F102) -> 1ASP | V102: 0.67 | W102: 22870 | X102: =V102*W102 -> 15322.9 | Y102: 0.1 | Z102: 0.1 | AB102: =L102-X102 -> 0 | AC102: =M102-Y102 -> 0 | AD102: =N102-Z102 -> 0
B103: 45343 | C103: SAMEMEC | D103: AMAT | E103: * | F103: 1ASP | G103: En efectivo (Moneda Extranjera) | H103: 45343 | I103: 45365 | J103: 0.32 | K103: 3420 | L103: 1094.4 | M103: 0.1 | N103: 0.1 | O103: 14/03/2024 | R103: =IF(C103="","",C103) -> SAMEMEC | S103: =IF(D103="","",D103) -> AMAT | T103: =IF(E103="","",E103) -> * | U103: =IF(F103="","",F103) -> 1ASP | V103: 0.32 | W103: 3420 | X103: =V103*W103 -> 1094.4 | Y103: 0.1 | Z103: 0.1 | AB103: =L103-X103 -> 0 | AC103: =M103-Y103 -> 0 | AD103: =N103-Z103 -> 0
B104: 45343 | C104: SAMEME1 | D104: AMAT | E104: * | F104: 1ASP | G104: En efectivo (Moneda Extranjera) | H104: 45343 | I104: 45365 | J104: 0.32 | K104: 4240 | L104: 1356.8 | M104: 0.1 | N104: 0.1 | O104: 14/03/2024 | R104: =IF(C104="","",C104) -> SAMEME1 | S104: =IF(D104="","",D104) -> AMAT | T104: =IF(E104="","",E104) -> * | U104: =IF(F104="","",F104) -> 1ASP | V104: 0.32 | W104: 4240 | X104: =V104*W104 -> 1356.8 | Y104: 0.1 | Z104: 0.1 | AB104: =L104-X104 -> 0 | AC104: =M104-Y104 -> 0 | AD104: =N104-Z104 -> 0
B105: 45343 | C105: SAMEME2 | D105: AMAT | E105: * | F105: 1ASP | G105: En efectivo (Moneda Extranjera) | H105: 45343 | I105: 45365 | J105: 0.32 | K105: 13450 | L105: 4304 | M105: 0.1 | N105: 0.1 | O105: 14/03/2024 | R105: =IF(C105="","",C105) -> SAMEME2 | S105: =IF(D105="","",D105) -> AMAT | T105: =IF(E105="","",E105) -> * | U105: =IF(F105="","",F105) -> 1ASP | V105: 0.32 | W105: 13450 | X105: =V105*W105 -> 4304 | Y105: 0.1 | Z105: 0.1 | AB105: =L105-X105 -> 0 | AC105: =M105-Y105 -> 0 | AD105: =N105-Z105 -> 0
B106: 45343 | C106: SAMEME2 | D106: META | E106: * | F106: 1ASP | G106: En efectivo (Moneda Extranjera) | H106: 45343 | I106: 45377 | J106: 0.5 | K106: 6910 | L106: 3455 | M106: 0.1 | N106: 0.1 | O106: 26/03/2024 | R106: =IF(C106="","",C106) -> SAMEME2 | S106: =IF(D106="","",D106) -> META | T106: =IF(E106="","",E106) -> * | U106: =IF(F106="","",F106) -> 1ASP | V106: 0.5 | W106: 6910 | X106: =V106*W106 -> 3455 | Y106: 0.1 | Z106: 0.1 | AB106: =L106-X106 -> 0 | AC106: =M106-Y106 -> 0 | AD106: =N106-Z106 -> 0
B107: 45343 | C107: SAM-RVG | D107: META | E107: * | F107: 1ASP | G107: En efectivo (Moneda Extranjera) | H107: 45343 | I107: 45377 | J107: 0.5 | K107: 4120 | L107: 2060 | M107: 0.1 | N107: 0.1 | O107: 26/03/2024 | R107: =IF(C107="","",C107) -> SAM-RVG | S107: =IF(D107="","",D107) -> META | T107: =IF(E107="","",E107) -> * | U107: =IF(F107="","",F107) -> 1ASP | V107: 0.5 | W107: 4120 | X107: =V107*W107 -> 2060 | Y107: 0.1 | Z107: 0.1 | AB107: =L107-X107 -> 0 | AC107: =M107-Y107 -> 0 | AD107: =N107-Z107 -> 0
B108: 45343 | C108: USA-EQ | D108: META | E108: * | F108: 1ASP | G108: En efectivo (Moneda Extranjera) | H108: 45343 | I108: 45377 | J108: 0.5 | K108: 46750 | L108: 23375 | M108: 0.1 | N108: 0.1 | O108: 26/03/2024 | R108: =IF(C108="","",C108) -> USA-EQ | S108: =IF(D108="","",D108) -> META | T108: =IF(E108="","",E108) -> * | U108: =IF(F108="","",F108) -> 1ASP | V108: 0.5 | W108: 46750 | X108: =V108*W108 -> 23375 | Y108: 0.1 | Z108: 0.1 | AB108: =L108-X108 -> 0 | AC108: =M108-Y108 -> 0 | AD108: =N108-Z108 -> 0
B109: 45344 | C109: SAM-RED | D109: AZN | E109: N | F109: 1ASP | G109: En efectivo (Moneda Extranjera) | H109: 45344 | I109: 45376 | J109: 0.985 | K109: 2010 | L109: 1979.85 | M109: 0.1 | N109: 0.1 | O109: 25/03/2024 | R109: =IF(C109="","",C109) -> SAM-RED | S109: =IF(D109="","",D109) -> AZN | T109: =IF(E109="","",E109) -> N | U109: =IF(F109="","",F109) -> 1ASP | V109: 0.985 | W109: 2010 | X109: =V109*W109 -> 1979.85 | Y109: 0.1 | Z109: 0.1 | AB109: =L109-X109 -> 0 | AC109: =M109-Y109 -> 0 | AD109: =N109-Z109 -> 0
B110: 45344 | C110: SAM-RVG | D110: AZN | E110: N | F110: 1ASP | G110: En efectivo (Moneda Extranjera) | H110: 45344 | I110: 45376 | J110: 0.985 | K110: 13230 | L110: 13031.55 | M110: 0.1 | N110: 0.1 | O110: 25/03/2024 | R110: =IF(C110="","",C110) -> SAM-RVG | S110: =IF(D110="","",D110) -> AZN | T110: =IF(E110="","",E110) -> N | U110: =IF(F110="","",F110) -> 1ASP | V110: 0.985 | W110: 13230 | X110: =V110*W110 -> 13031.55 | Y110: 0.1 | Z110: 0.1 | AB110: =L110-X110 -> 0 | AC110: =M110-Y110 -> 0 | AD110: =N110-Z110 -> 0
...

Sheet Div2
A1: Posición | B1: SI
A2: Fecha Registro | B2: (Todas) | O2: Ruta Archivos:
A3: Ex date/Efectos | B3: (Todas) | O3: C:\Home Office\Conciliaciones\
A5: Fondo | B5: Tipo de derecho | C5: Estatus | D5: ISIN | E5: Fecha Pago | F5: Proporción/importe
A6: 1A_PG_* | B6: Dividendo en efectivo | C6: Aplicado | D6: US7427181091 | E6: 17/08/2026 | F6: Option Number: "001" Option Type: "Cash" Default Option: "Yes" Gross Dividend Rate: "1.0885 USD" Option Number: "002" Option Type: "Security" Default Option: "No"
A7: FF_FVIA_16 | B7: Distribución en efectivo | C7: Aplicado | D7: MXFFFV000007 | E7: 27/07/2026 | F7: SERIE(S) '16' CUPON VIGENTE 0 CUPON PAGO 0 A MXN $ 0.3889785940707460
G23: 0.2121 - Tasa actual - Tasa de impuestos Impo | H23: rte | I23: ne | J23: to: | K23: Mone | L23: da: | M23: EUR | N23: Mon | O23: to: | P23: 0 | Q23: 15 | R23: 9075 | S23: {=- T} -> #NAME? | T23: asa actual Proporción - Opción 2 Importe bruto: Moneda: GBP Monto: 0.1814040396 - Tasa de referencia - Tasa de impuestos Importe neto: Moneda: GBP Monto: 0.1360530297 - Tasa de referencia
G24: 0.69 - Tasa actual - Porción de ingreso
G25: 0.157 - Tasa actual - Porción de ingreso Impo | H25: rte | I25: ne | J25: to: | K25: Mone | L25: da: | M25: GBP | N25: Mon | O25: to: | P25: 0 | Q25: 15 | R25: -7 | S25: Tasa | T25: actual Proporción - Opción 2
G26: 0.1 - Tasa actual - Tasa de impuestos Importe | H26: n | I26: eto: | J26: Mo | K26: neda: | L26: EU | M26: R Mo | N26: nto: | O26: 0 | P26: 65 | Q26: - | R26: Tas | S26: a ac | T26: tual
G27: 0.0237 - Tasa actual - Porción de ingreso
G28: 0.1062 - Tasa actual - Porción de ingreso
G29: 0.1934 - Tasa actual - Porción de ingreso
G30: 1.665327 - Tasa actual - Porción de ingreso
G31: 0.044 - Tasa actual - Porción de ingreso
G32: 0.360315 - Tasa actual - Porción de ingreso

Sheet Temp
D1: TRUE
